Workbook

Sheet Инструкция
B2: Модель TCO (Total Cost of Ownership) — кейс «Africa Delivery», горизонт 5 лет
B4: Зачем этот файл
B5: Задача | C5: Оценить полную стоимость владения выбранным архитектурным вариантом на 5 лет и использовать цифры как аргумент в ADR №1 («Выбор архитектурного стиля»).
B6: Как использовать | C6: Заполни один и тот же шаблон для каждого рассматриваемого варианта (например: модульный монолит / SOA / микросервисы) — сравнивать нужно итоги, а не ощущения.
B8: Цветовая легенда
B9: Синий текст на жёлтом фоне | C9: Ячейки для заполнения. Только их и редактируем.
B10: Чёрный текст | C10: Формулы. Не трогаем — пересчитаются сами.
B11: Зелёный текст | C11: Ссылка на лист «Допущения».
B13: Порядок работы
B14: Шаг 1 | C14: Лист «Допущения» → блок 1: вбить драйверы бизнеса по годам (активные пользователи, число заказов, средний чек). Из них считается GMV.
B15: Шаг 2 | C15: Лист «Допущения» → блок 2: финансовые допущения (инфляция, рост ФОТ, ставка дисконтирования, резерв, целевой SLO).
B16: Шаг 3 | C16: Лист «TCO» → в колонке «База, $/год (Год 1)» указать затраты первого года по каждой статье. Лишние статьи оставить пустыми, свои — дописать в свободные строки.
B17: Шаг 4 | C17: Лист «TCO» → в колонке «Драйвер роста» выбрать из выпадающего списка, от чего растёт статья: фикс / инфляция / ФОТ / пользователи / заказы / GMV. Годы 2–5 посчитаются сами.
B18: Шаг 5 | C18: Посмотреть блок «Ключевые метрики» внизу листа TCO: итог за 5 лет, NPV, стоимость на заказ, проверку бюджета CFO ($5k/мес на облако и SaaS — исправлено с $9k шаблона).
B20: Что важно не забыть в этом кейсе
B21: Бюджет CFO | C21: $5 000/мес на облако и SaaS — жёсткий потолок первые 6 месяцев (A6 п.1). $9 000 — цифра из презентации для борда, разработке недоступна. Если Год 1 не проходит — это архитектурное решение: опиши, что урезаешь.
B22: Цена простоя | C22: Инвестор оценивает минуту простоя в $12 000. Целевой SLO 99,99% = 52,6 мин/год ≈ $631k. Этот риск считается отдельным блоком — сравни его со стоимостью резервирования.
B23: Транзакционные расходы | C23: Комиссии M-Pesa / Flutterwave / Paystack, SMS и WhatsApp растут с GMV и числом заказов и на горизонте 5 лет обычно обгоняют инфраструктуру. Не забудь их — это типичная ошибка.
B24: Сравнение вариантов | C24: Транзакционные расходы (блок 3) почти одинаковы для любой архитектуры — это pass-through от оборота. Варианты архитектуры сравнивай по блокам 1, 2, 4 и 6.
B25: Разовые затраты | C25: Комплаенс-аудит NDPR/POPIA, пентест, миграция — если статья возникает не каждый год, просто перезапиши формулу в нужной ячейке года числом (и покрась в синий).
B26: Люди | C26: ФОТ команды — обычно самая крупная статья TCO. Микросервисы дешевле в масштабировании, но дороже в эксплуатации: это должно быть видно в цифрах, а не только в тексте ADR.
B28: Все числа в файле — примеры для демонстрации формата. Замени их своими оценками и укажи источник в колонке «Комментарий / источник».
B30: Изменения относительно шаблона (Africa Delivery, Task2):
B31: 1. Лимит CFO исправлен с $9 000 на $5 000 (A6 п.1); проверка лимита учитывает облако + SaaS (E63/E64).
B32: 2. Три копии листа TCO — по одной на вариант A, B, C; численность FTE — колонки N–R, ФОТ = FTE × ставка × индекс.
B33: 3. Блок 6: SLO и цена минуты простоя — по годам (лист «Допущения», стр. 35–41), переключатель режима 1/2.
B34: 4. Синие числа в годовых ячейках — ручные значения (разовые статьи, лестница SLO/DR, дежурства).
B35: 5. Листы «Сравнение» и «Стоимость ошибки» — две цифры для CFO: стоимость заказа и цена ошибки.

Sheet Допущения
B2: Допущения модели TCO — Africa Delivery
B3: Заполняются только ячейки с жёлтой заливкой. Все числа ниже — пример, заменить своими.
B5: 1. Драйверы бизнеса — заполнить
B6: Показатель | C6: Год 1 | D6: Год 2 | E6: Год 3 | F6: Год 4 | G6: Год 5 | H6: Комментарий / источник
B7: Активные пользователи (на конец года) | C7: 1000000 | D7: 2500000 | E7: 5000000 | F7: 7000000 | G7: 9000000 | H7: 1 млн+ к 12 мес. (У «Цели бизнеса»), 40% рынка за 3 года (A7) — бизнес-план инвестора. Сценарий 50 тыс. — лист «Стоимость ошибки»
B8: Число заказов в год | C8: 1500000 | D8: 6000000 | E8: 15000000 | F8: 24000000 | G8: 32000000 | H8: ≈3–4 заказа на активного пользователя в год; рамп Г1: 25 тыс./мес на запуске → 250 тыс./мес к 12-му месяцу
B9: Средний чек (AOV), $ | C9: 22 | D9: 23 | E9: 24 | F9: 25 | G9: 26 | H9: Ставка на низкую цену (У). Jumia ≈ $40 GMV/заказ — мы ниже
B10: GMV, $ в год (расчёт) | C10: =C8*C9 -> 33000000 | D10: =D8*D9 -> 138000000 | E10: =E8*E9 -> 360000000 | F10: =F8*F9 -> 600000000 | G10: =G8*G9 -> 832000000 | H10: Расчёт: заказы × средний чек
B12: 2. Финансовые допущения — заполнить
B13: Параметр | C13: Значение | H13: Комментарий / источник
B14: Инфляция затрат, % в год | C14: 0.05 | H14: Контракты в USD (облако, SaaS) — ниже локальной инфляции
B15: Рост ФОТ, % в год | C15: 0.1 | H15: Дефицит Go/SRE на рынке
B16: Ставка дисконтирования, % в год | C16: 0.25 | H16: Стартап, runway 9 мес. (A6 п.3) — высокая ставка
B17: Резерв на непредвиденное (contingency), % | C17: 0.15 | H17: Конус неопределённости
B18: Бюджет CFO на облако, $/мес | C18: 5000 | H18: ИСПРАВЛЕНО: $5 000 — жёсткий потолок (A6 п.1). $9 000 из шаблона — цифра борда, разработке недоступна
B19: Стоимость минуты простоя, $ | C19: 12000 | H19: Оценка инвестора (A1, A7) — пиковая минута распродажи (AS-08)
B20: Целевой SLO (доступность), % | C20: 0.999 | H20: Не используется: SLO заданы по вариантам и годам в строках 40–42
B21: Учитывать стоимость простоя в TCO (1 — да, 0 — нет) | C21: 1 | H21: Переключатель для сценарного анализа
B23: 3. Индексы роста — расчёт, не редактировать
B24: Драйвер | C24: Год 1 | D24: Год 2 | E24: Год 3 | F24: Год 4 | G24: Год 5 | H24: Как считается
B25: фикс | C25: 1 | D25: 1 | E25: 1 | F25: 1 | G25: 1 | H25: Затраты не меняются по годам
B26: инфляция | C26: 1 | D26: =C26*(1+$C$14) -> 1.05 | E26: =D26*(1+$C$14) -> 1.1025 | F26: =E26*(1+$C$14) -> 1.157625 | G26: =F26*(1+$C$14) -> 1.2155063 | H26: Год N = Год N-1 × (1 + инфляция)
B27: ФОТ | C27: 1 | D27: =C27*(1+$C$15) -> 1.1 | E27: =D27*(1+$C$15) -> 1.21 | F27: =E27*(1+$C$15) -> 1.331 | G27: =F27*(1+$C$15) -> 1.4641 | H27: Год N = Год N-1 × (1 + рост ФОТ)
B28: пользователи | C28: =C7/$C$7 -> 1 | D28: =D7/$C$7 -> 2.5 | E28: =E7/$C$7 -> 5 | F28: =F7/$C$7 -> 7 | G28: =G7/$C$7 -> 9 | H28: Пропорционально числу активных пользователей
B29: заказы | C29: =C8/$C$8 -> 1 | D29: =D8/$C$8 -> 4 | E29: =E8/$C$8 -> 10 | F29: =F8/$C$8 -> 16 | G29: =G8/$C$8 -> 21.333333 | H29: Пропорционально числу заказов
B30: GMV | C30: =C10/$C$10 -> 1 | D30: =D10/$C$10 -> 4.1818182 | E30: =E10/$C$10 -> 10.909091 | F30: =F10/$C$10 -> 18.181818 | G30: =G10/$C$10 -> 25.212121 | H30: Пропорционально обороту
B32: Драйвер «пользователи» — упрощение: облачные расходы редко растут строго линейно (есть эффект масштаба и обратный эффект — рост нагрузки на БД). При желании введи свой драйвер отдельной строкой в таблице индексов.
B34: 4. Добавлено: цена простоя, SLO по вариантам и ставки команды — заполнить
B35: Коэффициент пика (сбои чаще под нагрузкой) | C35: 3 | H35: Простой в пик стоит дороже средней минуты
B36: Реалистичная цена минуты простоя, $ (GMV / 525 600 × пик) | C36: =C10/525600*$C$35 -> 188.35616 | D36: =D10/525600*$C$35 -> 787.67123 | E36: =E10/525600*$C$35 -> 2054.7945 | F36: =F10/525600*$C$35 -> 3424.6575 | G36: =G10/525600*$C$35 -> 4748.8584 | H36: Расчёт от GMV по годам
B37: Режим цены простоя: 1 — $12k каждую минуту (инвестор), 2 — от GMV | C37: 2 | H37: Переключатель сценария (лист «Сравнение» показывает оба)
B38: Цена минуты простоя для расчёта, $ | C38: =IF($C$37=1,$C$19,C36) -> 188.35616 | D38: =IF($C$37=1,$C$19,D36) -> 787.67123 | E38: =IF($C$37=1,$C$19,E36) -> 2054.7945 | F38: =IF($C$37=1,$C$19,F36) -> 3424.6575 | G38: =IF($C$37=1,$C$19,G36) -> 4748.8584 | H38: Используется в блоке 6 всех листов TCO
B39: SLO вариант A (лестница SLO по годам) | C39: 0.999 | D39: 0.9995 | E39: 0.9995 | F39: 0.9999 | G39: 0.9999 | H39: Г1 99,9% → Г2–3 99,95% → Г4–5 99,99% (ADR-001, Task3)
B40: SLO вариант B | C40: 0.9995 | D40: 0.9995 | E40: 0.9995 | F40: 0.9999 | G40: 0.9999 | H40: Warm standby с первого дня
B41: SLO вариант C | C41: 0.9999 | D41: 0.9999 | E41: 0.9999 | F41: 0.9999 | G41: 0.9999 | H41: Заявлено CTO (A5). Риск: команда без опыта Istio и мультикластера
B42: Ставка разработчика (контрактор), $/год | C42: 85000 | H42: ≈ $41/ч; рынок Африки $34–54/ч (secondtalent, 2026)
B43: Ставка SRE / платформа, $/год | C43: 100000 | H43: Дефицитный профиль

Sheet TCO A — модульный монолит
B2: TCO на 5 лет — A. Модульный монолит (Go + PostgreSQL), managed, partner-first
B3: Заполняем колонки «Драйвер роста» и «База, $/год (Год 1)». Годы 1–5 считаются автоматически.
N4: Численность, FTE (среднее за год)
B5: Статья затрат | C5: Драйвер роста | D5: База, $/год (Год 1) | E5: Год 1 | F5: Год 2 | G5: Год 3 | H5: Год 4 | I5: Год 5 | J5: Итого 5 лет | K5: Доля | L5: Комментарий / источник | N5: Год 1 | O5: Год 2 | P5: Год 3 | Q5: Год 4 | R5: Год 5
B6: БЛОК 1. Облачная инфраструктура (OpEx)
B7: Compute: ноды / контейнеры / serverless | C7: пользователи | D7: 5400 | E7: =IF($D7="","",$D7*INDEX(Допущения!$C$25:$G$30,MATCH($C7,Допущения!$B$25:$B$30,0),1)) -> 5400 | F7: =IF($D7="","",$D7*INDEX(Допущения!$C$25:$G$30,MATCH($C7,Допущения!$B$25:$B$30,0),2)) -> 13500 | G7: =IF($D7="","",$D7*INDEX(Допущения!$C$25:$G$30,MATCH($C7,Допущения!$B$25:$B$30,0),3)) -> 27000 | H7: =IF($D7="","",$D7*INDEX(Допущения!$C$25:$G$30,MATCH($C7,Допущения!$B$25:$B$30,0),4)) -> 37800 | I7: =IF($D7="","",$D7*INDEX(Допущения!$C$25:$G$30,MATCH($C7,Допущения!$B$25:$B$30,0),5)) -> 48600 | J7: =SUM(E7:I7) -> 132300 | L7: EKS ($73/мес) + 3–4 × m7g.large af-south-1 ($0,108/ч) + всплески
B8: Управляемые БД (PostgreSQL, реплики) | C8: пользователи | D8: 5600 | E8: =IF($D8="","",$D8*INDEX(Допущения!$C$25:$G$30,MATCH($C8,Допущения!$B$25:$B$30,0),1)) -> 5600 | F8: =IF($D8="","",$D8*INDEX(Допущения!$C$25:$G$30,MATCH($C8,Допущения!$B$25:$B$30,0),2)) -> 14000 | G8: =IF($D8="","",$D8*INDEX(Допущения!$C$25:$G$30,MATCH($C8,Допущения!$B$25:$B$30,0),3)) -> 28000 | H8: =IF($D8="","",$D8*INDEX(Допущения!$C$25:$G$30,MATCH($C8,Допущения!$B$25:$B$30,0),4)) -> 39200 | I8: =IF($D8="","",$D8*INDEX(Допущения!$C$25:$G$30,MATCH($C8,Допущения!$B$25:$B$30,0),5)) -> 50400 | J8: =SUM(E8:I8) -> 137200 | L8: RDS PostgreSQL Multi-AZ db.m6g.large ($153/мес ×2) + read replica t4g.large для аналитики
B9: Хранилище объектов и резервные копии | C9: пользователи | D9: 840 | E9: =IF($D9="","",$D9*INDEX(Допущения!$C$25:$G$30,MATCH($C9,Допущения!$B$25:$B$30,0),1)) -> 840 | F9: =IF($D9="","",$D9*INDEX(Допущения!$C$25:$G$30,MATCH($C9,Допущения!$B$25:$B$30,0),2)) -> 2100 | G9: =IF($D9="","",$D9*INDEX(Допущения!$C$25:$G$30,MATCH($C9,Допущения!$B$25:$B$30,0),3)) -> 4200 | H9: =IF($D9="","",$D9*INDEX(Допущения!$C$25:$G$30,MATCH($C9,Допущения!$B$25:$B$30,0),4)) -> 5880 | I9: =IF($D9="","",$D9*INDEX(Допущения!$C$25:$G$30,MATCH($C9,Допущения!$B$25:$B$30,0),5)) -> 7560 | J9: =SUM(E9:I9) -> 20580 | L9: S3 af-south-1, фото товаров (WebP), бэкапы
B10: CDN и исходящий трафик | C10: пользователи | D10: 9800 | E10: =IF($D10="","",$D10*INDEX(Допущения!$C$25:$G$30,MATCH($C10,Допущения!$B$25:$B$30,0),1)) -> 9800 | F10: =IF($D10="","",$D10*INDEX(Допущения!$C$25:$G$30,MATCH($C10,Допущения!$B$25:$B$30,0),2)) -> 24500 | G10: =IF($D10="","",$D10*INDEX(Допущения!$C$25:$G$30,MATCH($C10,Допущения!$B$25:$B$30,0),3)) -> 49000 | H10: =IF($D10="","",$D10*INDEX(Допущения!$C$25:$G$30,MATCH($C10,Допущения!$B$25:$B$30,0),4)) -> 68600 | I10: =IF($D10="","",$D10*INDEX(Допущения!$C$25:$G$30,MATCH($C10,Допущения!$B$25:$B$30,0),5)) -> 88200 | J10: =SUM(E10:I10) -> 240100 | L10: CloudFront Африка $0,11/ГБ после 1 ТБ; ~15 МБ/MAU/мес (миниатюры WebP, кеш в приложении)
B11: Очереди / стриминг (Kafka, SQS) | C11: пользователи | D11: 840 | E11: 840 | F11: 8000 | G11: 14000 | H11: 20000 | I11: 26000 | J11: =SUM(E11:I11) -> 68840 | L11: MVP: outbox в PostgreSQL + SQS, Valkey (кеш). Managed Kafka (MSK) — с Года 2 при выделении сервисов
B12: Резервный регион / DR | C12: фикс | D12: 2400 | E12: 2400 | F12: 14400 | G12: 18000 | H12: 90000 | I12: 115000 | J12: =SUM(E12:I12) -> 239800 | L12: Лестница SLO: Г1 pilot light в GCP africa-south1 (бэкапы + IaC) → Г2–3 warm standby → Г4–5 active-active (99,99%)
B13: Локальное размещение данных (NDPR, Нигерия) | C13: пользователи | D13: 11900 | E13: =IF($D13="","",$D13*INDEX(Допущения!$C$25:$G$30,MATCH($C13,Допущения!$B$25:$B$30,0),1)) -> 11900 | F13: =IF($D13="","",$D13*INDEX(Допущения!$C$25:$G$30,MATCH($C13,Допущения!$B$25:$B$30,0),2)) -> 29750 | G13: =IF($D13="","",$D13*INDEX(Допущения!$C$25:$G$30,MATCH($C13,Допущения!$B$25:$B$30,0),3)) -> 59500 | H13: =IF($D13="","",$D13*INDEX(Допущения!$C$25:$G$30,MATCH($C13,Допущения!$B$25:$B$30,0),4)) -> 83300 | I13: =IF($D13="","",$D13*INDEX(Допущения!$C$25:$G$30,MATCH($C13,Допущения!$B$25:$B$30,0),5)) -> 107100 | J13: =SUM(E13:I13) -> 291550 | L13: Ячейка Нигерии в AWS Local Zone Лагос: 2 × m5.xlarge (узлы EKS) + 2 × m5.xlarge PostgreSQL + EBS gp2 + ALB + NAT-инстанс; бэкапы на 2-й площадке в Нигерии (ADR-003)
B14: Сеть и окружения dev/stage | C14: пользователи | D14: 7480 | E14: =IF($D14="","",$D14*INDEX(Допущения!$C$25:$G$30,MATCH($C14,Допущения!$B$25:$B$30,0),1)) -> 7480 | F14: =IF($D14="","",$D14*INDEX(Допущения!$C$25:$G$30,MATCH($C14,Допущения!$B$25:$B$30,0),2)) -> 18700 | G14: =IF($D14="","",$D14*INDEX(Допущения!$C$25:$G$30,MATCH($C14,Допущения!$B$25:$B$30,0),3)) -> 37400 | H14: =IF($D14="","",$D14*INDEX(Допущения!$C$25:$G$30,MATCH($C14,Допущения!$B$25:$B$30,0),4)) -> 52360 | I14: =IF($D14="","",$D14*INDEX(Допущения!$C$25:$G$30,MATCH($C14,Допущения!$B$25:$B$30,0),5)) -> 67320 | J14: =SUM(E14:I14) -> 183260 | L14: Сеть и периметр (NAT, ALB, WAF, KMS, DNS) $2 680 + окружения dev/stage и нагрузочный контур ≈ $400/мес (namespaces в общем EKS, малый RDS для stage, всплески теста)
B15: Итого по блоку | E15: =SUM(E7:E14) -> 44260 | F15: =SUM(F7:F14) -> 124950 | G15: =SUM(G7:G14) -> 237100 | H15: =SUM(H7:H14) -> 397140 | I15: =SUM(I7:I14) -> 510180 | J15: =SUM(J7:J14) -> 1313630 | K15: =IFERROR(J15/$J$51,0) -> 0.017935225
B17: БЛОК 2. Лицензии, SaaS и инструменты
B18: Observability (метрики, логи, трейсинг) | C18: пользователи | D18: 1800 | E18: =IF($D18="","",$D18*INDEX(Допущения!$C$25:$G$30,MATCH($C18,Допущения!$B$25:$B$30,0),1)) -> 1800 | F18: =IF($D18="","",$D18*INDEX(Допущения!$C$25:$G$30,MATCH($C18,Допущения!$B$25:$B$30,0),2)) -> 4500 | G18: =IF($D18="","",$D18*INDEX(Допущения!$C$25:$G$30,MATCH($C18,Допущения!$B$25:$B$30,0),3)) -> 9000 | H18: =IF($D18="","",$D18*INDEX(Допущения!$C$25:$G$30,MATCH($C18,Допущения!$B$25:$B$30,0),4)) -> 12600 | I18: =IF($D18="","",$D18*INDEX(Допущения!$C$25:$G$30,MATCH($C18,Допущения!$B$25:$B$30,0),5)) -> 16200 | J18: =SUM(E18:I18) -> 44100 | L18: Grafana Cloud (метрики, логи, трейсы) + OpenTelemetry
B19: CI/CD, репозиторий, артефакты | C19: инфляция | D19: 1200 | E19: =IF($D19="","",$D19*INDEX(Допущения!$C$25:$G$30,MATCH($C19,Допущения!$B$25:$B$30,0),1)) -> 1200 | F19: =IF($D19="","",$D19*INDEX(Допущения!$C$25:$G$30,MATCH($C19,Допущения!$B$25:$B$30,0),2)) -> 1260 | G19: =IF($D19="","",$D19*INDEX(Допущения!$C$25:$G$30,MATCH($C19,Допущения!$B$25:$B$30,0),3)) -> 1323 | H19: =IF($D19="","",$D19*INDEX(Допущения!$C$25:$G$30,MATCH($C19,Допущения!$B$25:$B$30,0),4)) -> 1389.15 | I19: =IF($D19="","",$D19*INDEX(Допущения!$C$25:$G$30,MATCH($C19,Допущения!$B$25:$B$30,0),5)) -> 1458.6075 | J19: =SUM(E19:I19) -> 6630.7575 | L19: GitHub Team + Actions
B20: Безопасность: WAF, секреты, антифрод | C20: пользователи | D20: 600 | E20: =IF($D20="","",$D20*INDEX(Допущения!$C$25:$G$30,MATCH($C20,Допущения!$B$25:$B$30,0),1)) -> 600 | F20: =IF($D20="","",$D20*INDEX(Допущения!$C$25:$G$30,MATCH($C20,Допущения!$B$25:$B$30,0),2)) -> 1500 | G20: =IF($D20="","",$D20*INDEX(Допущения!$C$25:$G$30,MATCH($C20,Допущения!$B$25:$B$30,0),3)) -> 3000 | H20: =IF($D20="","",$D20*INDEX(Допущения!$C$25:$G$30,MATCH($C20,Допущения!$B$25:$B$30,0),4)) -> 4200 | I20: =IF($D20="","",$D20*INDEX(Допущения!$C$25:$G$30,MATCH($C20,Допущения!$B$25:$B$30,0),5)) -> 5400 | J20: =SUM(E20:I20) -> 14700 | L20: Антифрод PSP (встроен), сканеры зависимостей
B21: WhatsApp Business API (подписка) | C21: инфляция | D21: 600 | E21: =IF($D21="","",$D21*INDEX(Допущения!$C$25:$G$30,MATCH($C21,Допущения!$B$25:$B$30,0),1)) -> 600 | F21: =IF($D21="","",$D21*INDEX(Допущения!$C$25:$G$30,MATCH($C21,Допущения!$B$25:$B$30,0),2)) -> 630 | G21: =IF($D21="","",$D21*INDEX(Допущения!$C$25:$G$30,MATCH($C21,Допущения!$B$25:$B$30,0),3)) -> 661.5 | H21: =IF($D21="","",$D21*INDEX(Допущения!$C$25:$G$30,MATCH($C21,Допущения!$B$25:$B$30,0),4)) -> 694.575 | I21: =IF($D21="","",$D21*INDEX(Допущения!$C$25:$G$30,MATCH($C21,Допущения!$B$25:$B$30,0),5)) -> 729.30375 | J21: =SUM(E21:I21) -> 3315.3787 | L21: Платформенный сбор BSP WhatsApp
B22: Прочее ПО и подписки | C22: инфляция | D22: 1800 | E22: =IF($D22="","",$D22*INDEX(Допущения!$C$25:$G$30,MATCH($C22,Допущения!$B$25:$B$30,0),1)) -> 1800 | F22: =IF($D22="","",$D22*INDEX(Допущения!$C$25:$G$30,MATCH($C22,Допущения!$B$25:$B$30,0),2)) -> 1890 | G22: =IF($D22="","",$D22*INDEX(Допущения!$C$25:$G$30,MATCH($C22,Допущения!$B$25:$B$30,0),3)) -> 1984.5 | H22: =IF($D22="","",$D22*INDEX(Допущения!$C$25:$G$30,MATCH($C22,Допущения!$B$25:$B$30,0),4)) -> 2083.725 | I22: =IF($D22="","",$D22*INDEX(Допущения!$C$25:$G$30,MATCH($C22,Допущения!$B$25:$B$30,0),5)) -> 2187.9113 | J22: =SUM(E22:I22) -> 9946.1363 | L22: Трекер, дизайн, Sentry
B23: SMS/USSD-агрегатор (подписка) | C23: инфляция | D23: 1800 | E23: =IF($D23="","",$D23*INDEX(Допущения!$C$25:$G$30,MATCH($C23,Допущения!$B$25:$B$30,0),1)) -> 1800 | F23: =IF($D23="","",$D23*INDEX(Допущения!$C$25:$G$30,MATCH($C23,Допущения!$B$25:$B$30,0),2)) -> 1890 | G23: =IF($D23="","",$D23*INDEX(Допущения!$C$25:$G$30,MATCH($C23,Допущения!$B$25:$B$30,0),3)) -> 1984.5 | H23: =IF($D23="","",$D23*INDEX(Допущения!$C$25:$G$30,MATCH($C23,Допущения!$B$25:$B$30,0),4)) -> 2083.725 | I23: =IF($D23="","",$D23*INDEX(Допущения!$C$25:$G$30,MATCH($C23,Допущения!$B$25:$B$30,0),5)) -> 2187.9113 | J23: =SUM(E23:I23) -> 9946.1363 | L23: Подписка SMS/USSD-агрегатора (Africa's Talking), push (FCM бесплатно)
B24: Итого по блоку | E24: =SUM(E18:E23) -> 7800 | F24: =SUM(F18:F23) -> 11670 | G24: =SUM(G18:G23) -> 17953.5 | H24: =SUM(H18:H23) -> 23051.175 | I24: =SUM(I18:I23) -> 28163.734 | J24: =SUM(J18:J23) -> 88638.409 | K24: =IFERROR(J24/$J$51,0) -> 0.001210196
B26: БЛОК 3. Транзакционные расходы (Buy / Partner)
B27: Комиссии платёжных провайдеров | C27: GMV | D27: 594000 | E27: =IF($D27="","",$D27*INDEX(Допущения!$C$25:$G$30,MATCH($C27,Допущения!$B$25:$B$30,0),1)) -> 594000 | F27: =IF($D27="","",$D27*INDEX(Допущения!$C$25:$G$30,MATCH($C27,Допущения!$B$25:$B$30,0),2)) -> 2484000 | G27: =IF($D27="","",$D27*INDEX(Допущения!$C$25:$G$30,MATCH($C27,Допущения!$B$25:$B$30,0),3)) -> 6480000 | H27: =IF($D27="","",$D27*INDEX(Допущения!$C$25:$G$30,MATCH($C27,Допущения!$B$25:$B$30,0),4)) -> 10800000 | I27: =IF($D27="","",$D27*INDEX(Допущения!$C$25:$G$30,MATCH($C27,Допущения!$B$25:$B$30,0),5)) -> 14976000 | J27: =SUM(E27:I27) -> 35334000 | L27: 1,8% GMV (ADR-004): NG ≈60% GMV — Paystack 1,5% + ₦100 + НДС 7,5% ≈ 1,94% (основной), Flutterwave 2% + НДС ≈ 2,15% (резерв), наличные ≈1,5%; KE ≈40% — M-Pesa Buy Goods 0,55%; выплаты ≈0,1%; резерв на чарджбэки 0,2%. Лимит CFO ≤ 2,5% (A6 п.6)
B28: SMS-уведомления | C28: заказы | D28: 30000 | E28: =IF($D28="","",$D28*INDEX(Допущения!$C$25:$G$30,MATCH($C28,Допущения!$B$25:$B$30,0),1)) -> 30000 | F28: =IF($D28="","",$D28*INDEX(Допущения!$C$25:$G$30,MATCH($C28,Допущения!$B$25:$B$30,0),2)) -> 120000 | G28: =IF($D28="","",$D28*INDEX(Допущения!$C$25:$G$30,MATCH($C28,Допущения!$B$25:$B$30,0),3)) -> 300000 | H28: =IF($D28="","",$D28*INDEX(Допущения!$C$25:$G$30,MATCH($C28,Допущения!$B$25:$B$30,0),4)) -> 480000 | I28: =IF($D28="","",$D28*INDEX(Допущения!$C$25:$G$30,MATCH($C28,Допущения!$B$25:$B$30,0),5)) -> 640000 | J28: =SUM(E28:I28) -> 1570000 | L28: ≈3 SMS/заказ × $0,005 + OTP: $0,02/заказ (Africa's Talking, KE ≈ KES 0,8)
B29: WhatsApp-сообщения (за диалог) | C29: заказы | D29: 16500 | E29: =IF($D29="","",$D29*INDEX(Допущения!$C$25:$G$30,MATCH($C29,Допущения!$B$25:$B$30,0),1)) -> 16500 | F29: =IF($D29="","",$D29*INDEX(Допущения!$C$25:$G$30,MATCH($C29,Допущения!$B$25:$B$30,0),2)) -> 66000 | G29: =IF($D29="","",$D29*INDEX(Допущения!$C$25:$G$30,MATCH($C29,Допущения!$B$25:$B$30,0),3)) -> 165000 | H29: =IF($D29="","",$D29*INDEX(Допущения!$C$25:$G$30,MATCH($C29,Допущения!$B$25:$B$30,0),4)) -> 264000 | I29: =IF($D29="","",$D29*INDEX(Допущения!$C$25:$G$30,MATCH($C29,Допущения!$B$25:$B$30,0),5)) -> 352000 | J29: =SUM(E29:I29) -> 863500 | L29: 2 utility-сообщения продавцу/заказ: Meta $0,004 (KE) – $0,0068 (NG)
B30: Логистика: интеграции и комиссии партнёров | C30: заказы | D30: 225000 | E30: =IF($D30="","",$D30*INDEX(Допущения!$C$25:$G$30,MATCH($C30,Допущения!$B$25:$B$30,0),1)) -> 225000 | F30: =IF($D30="","",$D30*INDEX(Допущения!$C$25:$G$30,MATCH($C30,Допущения!$B$25:$B$30,0),2)) -> 900000 | G30: =IF($D30="","",$D30*INDEX(Допущения!$C$25:$G$30,MATCH($C30,Допущения!$B$25:$B$30,0),3)) -> 2250000 | H30: =IF($D30="","",$D30*INDEX(Допущения!$C$25:$G$30,MATCH($C30,Допущения!$B$25:$B$30,0),4)) -> 3600000 | I30: =IF($D30="","",$D30*INDEX(Допущения!$C$25:$G$30,MATCH($C30,Допущения!$B$25:$B$30,0),5)) -> 4800000 | J30: =SUM(E30:I30) -> 11775000 | L30: Доставку оплачивает покупатель (pass-through). Платформа платит обратную доставку по «бесплатному возврату 30 дней» (A2 обещ. 4): 6% × $2,5
B31: USSD-сессии и короткие коды | C31: заказы | D31: 10500 | E31: =IF($D31="","",$D31*INDEX(Допущения!$C$25:$G$30,MATCH($C31,Допущения!$B$25:$B$30,0),1)) -> 10500 | F31: =IF($D31="","",$D31*INDEX(Допущения!$C$25:$G$30,MATCH($C31,Допущения!$B$25:$B$30,0),2)) -> 42000 | G31: =IF($D31="","",$D31*INDEX(Допущения!$C$25:$G$30,MATCH($C31,Допущения!$B$25:$B$30,0),3)) -> 105000 | H31: =IF($D31="","",$D31*INDEX(Допущения!$C$25:$G$30,MATCH($C31,Допущения!$B$25:$B$30,0),4)) -> 168000 | I31: =IF($D31="","",$D31*INDEX(Допущения!$C$25:$G$30,MATCH($C31,Допущения!$B$25:$B$30,0),5)) -> 224000 | J31: =SUM(E31:I31) -> 549500 | L31: USSD-сессии ($0,005) + аренда короткого кода KE
B32: Итого по блоку | E32: =SUM(E27:E31) -> 876000 | F32: =SUM(F27:F31) -> 3612000 | G32: =SUM(G27:G31) -> 9300000 | H32: =SUM(H27:H31) -> 15312000 | I32: =SUM(I27:I31) -> 20992000 | J32: =SUM(J27:J31) -> 50092000 | K32: =IFERROR(J32/$J$51,0) -> 0.68391501
B34: БЛОК 4. Команда (ФОТ)
B35: Разработка (FTE × годовая ставка) | C35: ФОТ | D35: =N35*Допущения!$C$42 -> 510000 | E35: =N35*Допущения!$C$42*Допущения!C$27 -> 510000 | F35: =O35*Допущения!$C$42*Допущения!D$27 -> 841500 | G35: =P35*Допущения!$C$42*Допущения!E$27 -> 1439900 | H35: =Q35*Допущения!$C$42*Допущения!F$27 -> 2036430 | I35: =R35*Допущения!$C$42*Допущения!G$27 -> 2737867 | J35: =SUM(E35:I35) -> 7565697 | L35: FTE (колонки N–R) × ставка × индекс ФОТ | N35: 6 | O35: 9 | P35: 14 | Q35: 18 | R35: 22
B36: DevOps / SRE | C36: ФОТ | D36: =N36*Допущения!$C$43 -> 100000 | E36: =N36*Допущения!$C$43*Допущения!C$27 -> 100000 | F36: =O36*Допущения!$C$43*Допущения!D$27 -> 220000 | G36: =P36*Допущения!$C$43*Допущения!E$27 -> 363000 | H36: =Q36*Допущения!$C$43*Допущения!F$27 -> 665500 | I36: =R36*Допущения!$C$43*Допущения!G$27 -> 732050 | J36: =SUM(E36:I36) -> 2080550 | L36: FTE (колонки N–R) × ставка SRE × индекс ФОТ | N36: 1 | O36: 2 | P36: 3 | Q36: 5 | R36: 5
B37: Поддержка и дежурства 24/7 | C37: ФОТ | D37: 30000 | E37: 30000 | F37: 60000 | G37: 90000 | H37: 120000 | I37: 140000 | J37: =SUM(E37:I37) -> 440000 | L37: Дежурства: Г1 — надбавка on-call в команде; далее follow-the-sun
B38: Архитектура и менеджмент | C38: ФОТ | D38: 300000 | E38: =IF($D38="","",$D38*INDEX(Допущения!$C$25:$G$30,MATCH($C38,Допущения!$B$25:$B$30,0),1)) -> 300000 | F38: =IF($D38="","",$D38*INDEX(Допущения!$C$25:$G$30,MATCH($C38,Допущения!$B$25:$B$30,0),2)) -> 330000 | G38: =IF($D38="","",$D38*INDEX(Допущения!$C$25:$G$30,MATCH($C38,Допущения!$B$25:$B$30,0),3)) -> 363000 | H38: =IF($D38="","",$D38*INDEX(Допущения!$C$25:$G$30,MATCH($C38,Допущения!$B$25:$B$30,0),4)) -> 399300 | I38: =IF($D38="","",$D38*INDEX(Допущения!$C$25:$G$30,MATCH($C38,Допущения!$B$25:$B$30,0),5)) -> 439230 | J38: =SUM(E38:I38) -> 1831530 | L38: CTO + Solution Architect (одинаково во всех вариантах)
C39: фикс | E39: =IF($D39="","",$D39*INDEX(Допущения!$C$25:$G$30,MATCH($C39,Допущения!$B$25:$B$30,0),1)) | F39: =IF($D39="","",$D39*INDEX(Допущения!$C$25:$G$30,MATCH($C39,Допущения!$B$25:$B$30,0),2)) | G39: =IF($D39="","",$D39*INDEX(Допущения!$C$25:$G$30,MATCH($C39,Допущения!$B$25:$B$30,0),3)) | H39: =IF($D39="","",$D39*INDEX(Допущения!$C$25:$G$30,MATCH($C39,Допущения!$B$25:$B$30,0),4)) | I39: =IF($D39="","",$D39*INDEX(Допущения!$C$25:$G$30,MATCH($C39,Допущения!$B$25:$B$30,0),5)) | J39: =SUM(E39:I39) -> 0 | L39: Своя статья
B40: Итого по блоку | E40: =SUM(E35:E39) -> 940000 | F40: =SUM(F35:F39) -> 1451500 | G40: =SUM(G35:G39) -> 2255900 | H40: =SUM(H35:H39) -> 3221230 | I40: =SUM(I35:I39) -> 4049147 | J40: =SUM(J35:J39) -> 11917777 | K40: =IFERROR(J40/$J$51,0) -> 0.16271553
B42: БЛОК 5. Разовые затраты и комплаенс
B43: Юридический и комплаенс-аудит (NDPR, POPIA, KICA) | C43: фикс | D43: 30000 | E43: 30000 | F43: 15000 | G43: 15750 | H43: 16538 | I43: 17364 | J43: =SUM(E43:I43) -> 94652 | L43: Регистрация NDPC/ODPC/InfoReg, внешний DPO, ежегодный аудит NDPA (A3 п.1)
B44: Пентест и аудит безопасности | C44: инфляция | D44: 15000 | E44: =IF($D44="","",$D44*INDEX(Допущения!$C$25:$G$30,MATCH($C44,Допущения!$B$25:$B$30,0),1)) -> 15000 | F44: =IF($D44="","",$D44*INDEX(Допущения!$C$25:$G$30,MATCH($C44,Допущения!$B$25:$B$30,0),2)) -> 15750 | G44: =IF($D44="","",$D44*INDEX(Допущения!$C$25:$G$30,MATCH($C44,Допущения!$B$25:$B$30,0),3)) -> 16537.5 | H44: =IF($D44="","",$D44*INDEX(Допущения!$C$25:$G$30,MATCH($C44,Допущения!$B$25:$B$30,0),4)) -> 17364.375 | I44: =IF($D44="","",$D44*INDEX(Допущения!$C$25:$G$30,MATCH($C44,Допущения!$B$25:$B$30,0),5)) -> 18232.594 | J44: =SUM(E44:I44) -> 82884.469 | L44: Ежегодный пентест
B45: Миграция данных и интеграции при запуске | C45: фикс | D45: 15000 | E45: 15000 | F45: 0 | G45: 0 | H45: 0 | I45: 0 | J45: =SUM(E45:I45) -> 15000 | L45: Онбординг партнёров: PSP, Sendbox, перевозчик KE, D-U-N-S, сторы
B46: Обучение команды и найм | C46: фикс | D46: 10000 | E46: 10000 | F46: 15000 | G46: 20000 | H46: 20000 | I46: 20000 | J46: =SUM(E46:I46) -> 85000 | L46: Найм и обучение (рост команды с января)
C47: фикс | E47: =IF($D47="","",$D47*INDEX(Допущения!$C$25:$G$30,MATCH($C47,Допущения!$B$25:$B$30,0),1)) | F47: =IF($D47="","",$D47*INDEX(Допущения!$C$25:$G$30,MATCH($C47,Допущения!$B$25:$B$30,0),2)) | G47: =IF($D47="","",$D47*INDEX(Допущения!$C$25:$G$30,MATCH($C47,Допущения!$B$25:$B$30,0),3)) | H47: =IF($D47="","",$D47*INDEX(Допущения!$C$25:$G$30,MATCH($C47,Допущения!$B$25:$B$30,0),4)) | I47: =IF($D47="","",$D47*INDEX(Допущения!$C$25:$G$30,MATCH($C47,Допущения!$B$25:$B$30,0),5)) | J47: =SUM(E47:I47) -> 0 | L47: Своя статья
B48: Итого по блоку | E48: =SUM(E43:E47) -> 70000 | F48: =SUM(F43:F47) -> 45750 | G48: =SUM(G43:G47) -> 52287.5 | H48: =SUM(H43:H47) -> 53902.375 | I48: =SUM(I43:I47) -> 55596.594 | J48: =SUM(J43:J47) -> 277536.47 | K48: =IFERROR(J48/$J$51,0) -> 0.0037892549
B50: Резерв на непредвиденное (contingency) | E50: =(E15+E24+E32+E40+E48)*Допущения!$C$17 -> 290709 | F50: =(F15+F24+F32+F40+F48)*Допущения!$C$17 -> 786880.5 | G50: =(G15+G24+G32+G40+G48)*Допущения!$C$17 -> 1779486.1 | H50: =(H15+H24+H32+H40+H48)*Допущения!$C$17 -> 2851098.5 | I50: =(I15+I24+I32+I40+I48)*Допущения!$C$17 -> 3845263.1 | J50: =SUM(E50:I50) -> 9553437.3 | L50: Расчёт: сумма блоков 1–5 × ставка резерва с листа «Допущения»
B51: ИТОГО прямые затраты (TCO без учёта простоев) | E51: =E15+E24+E32+E40+E48+E50 -> 2228769 | F51: =F15+F24+F32+F40+F48+F50 -> 6032750.5 | G51: =G15+G24+G32+G40+G48+G50 -> 13642727 | H51: =H15+H24+H32+H40+H48+H50 -> 21858422 | I51: =I15+I24+I32+I40+I48+I50 -> 29480350 | J51: =SUM(E51:I51) -> 73243019
B52: БЛОК 6. Стоимость недоступности (риск)
B53: Ожидаемые потери от простоя (SLO и цена минуты — по годам, «Допущения» стр. 38–41) | E53: =(1-Допущения!C39)*525600*Допущения!C38*Допущения!$C$21 -> 99000 | F53: =(1-Допущения!D39)*525600*Допущения!D38*Допущения!$C$21 -> 207000 | G53: =(1-Допущения!E39)*525600*Допущения!E38*Допущения!$C$21 -> 540000 | H53: =(1-Допущения!F39)*525600*Допущения!F38*Допущения!$C$21 -> 180000 | I53: =(1-Допущения!G39)*525600*Допущения!G38*Допущения!$C$21 -> 249600 | J53: =SUM(E53:I53) -> 1275600 | L53: (1 − SLO года) × 525 600 мин × цена минуты года × переключатель
B54: ИТОГО TCO с учётом стоимости простоя | E54: =E51+E53 -> 2327769 | F54: =F51+F53 -> 6239750.5 | G54: =G51+G53 -> 14182727 | H54: =H51+H53 -> 22038422 | I54: =I51+I53 -> 29729950 | J54: =SUM(E54:I54) -> 74518619
B55: Коэффициент дисконтирования | E55: =1/(1+Допущения!$C$16)^0 -> 1 | F55: =1/(1+Допущения!$C$16)^1 -> 0.8 | G55: =1/(1+Допущения!$C$16)^2 -> 0.64 | H55: =1/(1+Допущения!$C$16)^3 -> 0.512 | I55: =1/(1+Допущения!$C$16)^4 -> 0.4096
B56: Дисконтированный TCO (NPV затрат) | E56: =E54*E55 -> 2327769 | F56: =F54*F55 -> 4991800.4 | G56: =G54*G55 -> 9076945.4 | H56: =H54*H55 -> 11283672 | I56: =I54*I55 -> 12177388 | J56: =SUM(E56:I56) -> 39857575
B58: Ключевые метрики
B59: TCO за 5 лет, прямые затраты | E59: =J51 -> 73243019 | L59: Основная цифра для сравнения вариантов в ADR
B60: TCO за 5 лет с учётом простоя | E60: =J54 -> 74518619 | L60: Показывает цену недоступности для mission critical
B61: NPV затрат за 5 лет | E61: =J56 -> 39857575 | L61: Затраты, приведённые к сегодняшнему дню
B62: Средние затраты в год | E62: =J51/5 -> 14648604 | L62: Ориентир для планирования бюджета
B63: Облако + SaaS, $/мес в Год 1 (A6 п.1: лимит включает SaaS) | E63: =(E15+E24)/12 -> 4338.3333 | L63: Сравнивается с лимитом CFO
B64: Проверка бюджета CFO на Год 1 | E64: =IF((E15+E24)/12<=Допущения!$C$18,"В бюджете CFO","ПРЕВЫШЕНИЕ бюджета") -> В бюджете CFO | L64: Если превышение — объясни в ADR, чем жертвуешь
B65: TCO на 1 заказ за 5 лет | E65: =IFERROR(J51/SUM(Допущения!$C$8:$G$8),0) -> 0.93303209 | L65: Юнит-экономика: сколько ИТ стоит в одном заказе
B66: TCO на 1 активного пользователя (Год 5) | E66: =IFERROR(I51/Допущения!$G$7,0) -> 3.2755945 | L66: Проверка масштабируемости модели
B67: Затраты ИТ как доля GMV за 5 лет | E67: =IFERROR(J51/SUM(Допущения!$C$10:$G$10),0) -> 0.037311777 | L67: Здоровый маркетплейс — единицы процентов
B68: Доля облачной инфраструктуры в TCO | E68: =IFERROR(J15/J51,0) -> 0.017935225 | L68: Обычно меньше, чем ожидают студенты
B69: Доля транзакционных расходов в TCO | E69: =IFERROR(J32/J51,0) -> 0.68391501 | L69: Растёт быстрее всего вместе с GMV
B70: Доля команды (ФОТ) в TCO | E70: =IFERROR(J40/J51,0) -> 0.16271553 | L70: Как правило, крупнейшая статья
B72: Вывод для ADR (заполнить текстом): какой вариант дешевле, за счёт чего, и какие допущения сильнее всего влияют на результат?
B73: Самый дешёвый: на 3–4 FTE меньше B и на 10–12 FTE меньше C, без лицензий, облако+SaaS ≈ $4.3k/мес < $5k. Плата — больше простоя на старте (99,9%), но цена минуты в Г1 ≈ $190, а не $12k. SLO растёт по лестнице вместе с GMV. Сильнее всего результат зависит от численности команды и цены минуты простоя.

Sheet TCO B — сервисы (SOA)
B2: TCO на 5 лет — B. 7 доменных сервисов, managed K8s + managed Kafka, БД на сервис
B3: Заполняем колонки «Драйвер роста» и «База, $/год (Год 1)». Годы 1–5 считаются автоматически.
N4: Численность, FTE (среднее за год)
B5: Статья затрат | C5: Драйвер роста | D5: База, $/год (Год 1) | E5: Год 1 | F5: Год 2 | G5: Год 3 | H5: Год 4 | I5: Год 5 | J5: Итого 5 лет | K5: Доля | L5: Комментарий / источник | N5: Год 1 | O5: Год 2 | P5: Год 3 | Q5: Год 4 | R5: Год 5
B6: БЛОК 1. Облачная инфраструктура (OpEx)
B7: Compute: ноды / контейнеры / serverless | C7: пользователи | D7: 9660 | E7: =IF($D7="","",$D7*INDEX(Допущения!$C$25:$G$30,MATCH($C7,Допущения!$B$25:$B$30,0),1)) -> 9660 | F7: =IF($D7="","",$D7*INDEX(Допущения!$C$25:$G$30,MATCH($C7,Допущения!$B$25:$B$30,0),2)) -> 24150 | G7: =IF($D7="","",$D7*INDEX(Допущения!$C$25:$G$30,MATCH($C7,Допущения!$B$25:$B$30,0),3)) -> 48300 | H7: =IF($D7="","",$D7*INDEX(Допущения!$C$25:$G$30,MATCH($C7,Допущения!$B$25:$B$30,0),4)) -> 67620 | I7: =IF($D7="","",$D7*INDEX(Допущения!$C$25:$G$30,MATCH($C7,Допущения!$B$25:$B$30,0),5)) -> 86940 | J7: =SUM(E7:I7) -> 236670 | L7: EKS + 8 × m7g.large: 7 сервисов × ≥2 реплики + шлюз
B8: Управляемые БД (PostgreSQL, реплики) | C8: пользователи | D8: 12960 | E8: =IF($D8="","",$D8*INDEX(Допущения!$C$25:$G$30,MATCH($C8,Допущения!$B$25:$B$30,0),1)) -> 12960 | F8: =IF($D8="","",$D8*INDEX(Допущения!$C$25:$G$30,MATCH($C8,Допущения!$B$25:$B$30,0),2)) -> 32400 | G8: =IF($D8="","",$D8*INDEX(Допущения!$C$25:$G$30,MATCH($C8,Допущения!$B$25:$B$30,0),3)) -> 64800 | H8: =IF($D8="","",$D8*INDEX(Допущения!$C$25:$G$30,MATCH($C8,Допущения!$B$25:$B$30,0),4)) -> 90720 | I8: =IF($D8="","",$D8*INDEX(Допущения!$C$25:$G$30,MATCH($C8,Допущения!$B$25:$B$30,0),5)) -> 116640 | J8: =SUM(E8:I8) -> 317520 | L8: 4 кластера RDS Multi-AZ db.t4g.large + read replica
B9: Хранилище объектов и резервные копии | C9: пользователи | D9: 1000 | E9: =IF($D9="","",$D9*INDEX(Допущения!$C$25:$G$30,MATCH($C9,Допущения!$B$25:$B$30,0),1)) -> 1000 | F9: =IF($D9="","",$D9*INDEX(Допущения!$C$25:$G$30,MATCH($C9,Допущения!$B$25:$B$30,0),2)) -> 2500 | G9: =IF($D9="","",$D9*INDEX(Допущения!$C$25:$G$30,MATCH($C9,Допущения!$B$25:$B$30,0),3)) -> 5000 | H9: =IF($D9="","",$D9*INDEX(Допущения!$C$25:$G$30,MATCH($C9,Допущения!$B$25:$B$30,0),4)) -> 7000 | I9: =IF($D9="","",$D9*INDEX(Допущения!$C$25:$G$30,MATCH($C9,Допущения!$B$25:$B$30,0),5)) -> 9000 | J9: =SUM(E9:I9) -> 24500 | L9: S3
B10: CDN и исходящий трафик | C10: пользователи | D10: 9800 | E10: =IF($D10="","",$D10*INDEX(Допущения!$C$25:$G$30,MATCH($C10,Допущения!$B$25:$B$30,0),1)) -> 9800 | F10: =IF($D10="","",$D10*INDEX(Допущения!$C$25:$G$30,MATCH($C10,Допущения!$B$25:$B$30,0),2)) -> 24500 | G10: =IF($D10="","",$D10*INDEX(Допущения!$C$25:$G$30,MATCH($C10,Допущения!$B$25:$B$30,0),3)) -> 49000 | H10: =IF($D10="","",$D10*INDEX(Допущения!$C$25:$G$30,MATCH($C10,Допущения!$B$25:$B$30,0),4)) -> 68600 | I10: =IF($D10="","",$D10*INDEX(Допущения!$C$25:$G$30,MATCH($C10,Допущения!$B$25:$B$30,0),5)) -> 88200 | J10: =SUM(E10:I10) -> 240100 | L10: CloudFront (как в A)
B11: Очереди / стриминг (Kafka, SQS) | C11: пользователи | D11: 6960 | E11: =IF($D11="","",$D11*INDEX(Допущения!$C$25:$G$30,MATCH($C11,Допущения!$B$25:$B$30,0),1)) -> 6960 | F11: =IF($D11="","",$D11*INDEX(Допущения!$C$25:$G$30,MATCH($C11,Допущения!$B$25:$B$30,0),2)) -> 17400 | G11: =IF($D11="","",$D11*INDEX(Допущения!$C$25:$G$30,MATCH($C11,Допущения!$B$25:$B$30,0),3)) -> 34800 | H11: =IF($D11="","",$D11*INDEX(Допущения!$C$25:$G$30,MATCH($C11,Допущения!$B$25:$B$30,0),4)) -> 48720 | I11: =IF($D11="","",$D11*INDEX(Допущения!$C$25:$G$30,MATCH($C11,Допущения!$B$25:$B$30,0),5)) -> 62640 | J11: =SUM(E11:I11) -> 170520 | L11: Amazon MSK 3 × kafka.m7g.large
B12: Резервный регион / DR | C12: фикс | D12: 14400 | E12: 14400 | F12: 18000 | G12: 24000 | H12: 100000 | I12: 125000 | J12: =SUM(E12:I12) -> 281400 | L12: Warm standby в GCP africa-south1 с первого дня (99,95%) → active-active к Г4
B13: Локальное размещение данных (NDPR, Нигерия) | C13: пользователи | D13: 16800 | E13: =IF($D13="","",$D13*INDEX(Допущения!$C$25:$G$30,MATCH($C13,Допущения!$B$25:$B$30,0),1)) -> 16800 | F13: =IF($D13="","",$D13*INDEX(Допущения!$C$25:$G$30,MATCH($C13,Допущения!$B$25:$B$30,0),2)) -> 42000 | G13: =IF($D13="","",$D13*INDEX(Допущения!$C$25:$G$30,MATCH($C13,Допущения!$B$25:$B$30,0),3)) -> 84000 | H13: =IF($D13="","",$D13*INDEX(Допущения!$C$25:$G$30,MATCH($C13,Допущения!$B$25:$B$30,0),4)) -> 117600 | I13: =IF($D13="","",$D13*INDEX(Допущения!$C$25:$G$30,MATCH($C13,Допущения!$B$25:$B$30,0),5)) -> 151200 | J13: =SUM(E13:I13) -> 411600 | L13: Ячейка Нигерии: больше узлов (сервисы) + PostgreSQL ×2
B14: Сеть, OpenSearch, окружения | C14: пользователи | D14: 17900 | E14: =IF($D14="","",$D14*INDEX(Допущения!$C$25:$G$30,MATCH($C14,Допущения!$B$25:$B$30,0),1)) -> 17900 | F14: =IF($D14="","",$D14*INDEX(Допущения!$C$25:$G$30,MATCH($C14,Допущения!$B$25:$B$30,0),2)) -> 44750 | G14: =IF($D14="","",$D14*INDEX(Допущения!$C$25:$G$30,MATCH($C14,Допущения!$B$25:$B$30,0),3)) -> 89500 | H14: =IF($D14="","",$D14*INDEX(Допущения!$C$25:$G$30,MATCH($C14,Допущения!$B$25:$B$30,0),4)) -> 125300 | I14: =IF($D14="","",$D14*INDEX(Допущения!$C$25:$G$30,MATCH($C14,Допущения!$B$25:$B$30,0),5)) -> 161100 | J14: =SUM(E14:I14) -> 438550 | L14: Сеть (NAT, ALB, WAF) $3 600 + OpenSearch 2 × r6g.large $3 500 + окружения dev/stage ≈ $900/мес
B15: Итого по блоку | E15: =SUM(E7:E14) -> 89480 | F15: =SUM(F7:F14) -> 205700 | G15: =SUM(G7:G14) -> 399400 | H15: =SUM(H7:H14) -> 625560 | I15: =SUM(I7:I14) -> 800720 | J15: =SUM(J7:J14) -> 2120860 | K15: =IFERROR(J15/$J$51,0) -> 0.027597193
B17: БЛОК 2. Лицензии, SaaS и инструменты
B18: Observability (метрики, логи, трейсинг) | C18: пользователи | D18: 4800 | E18: =IF($D18="","",$D18*INDEX(Допущения!$C$25:$G$30,MATCH($C18,Допущения!$B$25:$B$30,0),1)) -> 4800 | F18: =IF($D18="","",$D18*INDEX(Допущения!$C$25:$G$30,MATCH($C18,Допущения!$B$25:$B$30,0),2)) -> 12000 | G18: =IF($D18="","",$D18*INDEX(Допущения!$C$25:$G$30,MATCH($C18,Допущения!$B$25:$B$30,0),3)) -> 24000 | H18: =IF($D18="","",$D18*INDEX(Допущения!$C$25:$G$30,MATCH($C18,Допущения!$B$25:$B$30,0),4)) -> 33600 | I18: =IF($D18="","",$D18*INDEX(Допущения!$C$25:$G$30,MATCH($C18,Допущения!$B$25:$B$30,0),5)) -> 43200 | J18: =SUM(E18:I18) -> 117600 | L18: Grafana Cloud: больше сервисов — больше трейсов
B19: CI/CD, репозиторий, артефакты | C19: инфляция | D19: 2400 | E19: =IF($D19="","",$D19*INDEX(Допущения!$C$25:$G$30,MATCH($C19,Допущения!$B$25:$B$30,0),1)) -> 2400 | F19: =IF($D19="","",$D19*INDEX(Допущения!$C$25:$G$30,MATCH($C19,Допущения!$B$25:$B$30,0),2)) -> 2520 | G19: =IF($D19="","",$D19*INDEX(Допущения!$C$25:$G$30,MATCH($C19,Допущения!$B$25:$B$30,0),3)) -> 2646 | H19: =IF($D19="","",$D19*INDEX(Допущения!$C$25:$G$30,MATCH($C19,Допущения!$B$25:$B$30,0),4)) -> 2778.3 | I19: =IF($D19="","",$D19*INDEX(Допущения!$C$25:$G$30,MATCH($C19,Допущения!$B$25:$B$30,0),5)) -> 2917.215 | J19: =SUM(E19:I19) -> 13261.515 | L19: GitHub + Actions (7 пайплайнов)
B20: Безопасность: WAF, секреты, антифрод | C20: пользователи | D20: 1200 | E20: =IF($D20="","",$D20*INDEX(Допущения!$C$25:$G$30,MATCH($C20,Допущения!$B$25:$B$30,0),1)) -> 1200 | F20: =IF($D20="","",$D20*INDEX(Допущения!$C$25:$G$30,MATCH($C20,Допущения!$B$25:$B$30,0),2)) -> 3000 | G20: =IF($D20="","",$D20*INDEX(Допущения!$C$25:$G$30,MATCH($C20,Допущения!$B$25:$B$30,0),3)) -> 6000 | H20: =IF($D20="","",$D20*INDEX(Допущения!$C$25:$G$30,MATCH($C20,Допущения!$B$25:$B$30,0),4)) -> 8400 | I20: =IF($D20="","",$D20*INDEX(Допущения!$C$25:$G$30,MATCH($C20,Допущения!$B$25:$B$30,0),5)) -> 10800 | J20: =SUM(E20:I20) -> 29400 | L20: Секреты, сканеры, mTLS-сертификаты
B21: WhatsApp Business API (подписка) | C21: инфляция | D21: 600 | E21: =IF($D21="","",$D21*INDEX(Допущения!$C$25:$G$30,MATCH($C21,Допущения!$B$25:$B$30,0),1)) -> 600 | F21: =IF($D21="","",$D21*INDEX(Допущения!$C$25:$G$30,MATCH($C21,Допущения!$B$25:$B$30,0),2)) -> 630 | G21: =IF($D21="","",$D21*INDEX(Допущения!$C$25:$G$30,MATCH($C21,Допущения!$B$25:$B$30,0),3)) -> 661.5 | H21: =IF($D21="","",$D21*INDEX(Допущения!$C$25:$G$30,MATCH($C21,Допущения!$B$25:$B$30,0),4)) -> 694.575 | I21: =IF($D21="","",$D21*INDEX(Допущения!$C$25:$G$30,MATCH($C21,Допущения!$B$25:$B$30,0),5)) -> 729.30375 | J21: =SUM(E21:I21) -> 3315.3787 | L21: BSP WhatsApp
B22: Прочее ПО и подписки | C22: инфляция | D22: 1800 | E22: =IF($D22="","",$D22*INDEX(Допущения!$C$25:$G$30,MATCH($C22,Допущения!$B$25:$B$30,0),1)) -> 1800 | F22: =IF($D22="","",$D22*INDEX(Допущения!$C$25:$G$30,MATCH($C22,Допущения!$B$25:$B$30,0),2)) -> 1890 | G22: =IF($D22="","",$D22*INDEX(Допущения!$C$25:$G$30,MATCH($C22,Допущения!$B$25:$B$30,0),3)) -> 1984.5 | H22: =IF($D22="","",$D22*INDEX(Допущения!$C$25:$G$30,MATCH($C22,Допущения!$B$25:$B$30,0),4)) -> 2083.725 | I22: =IF($D22="","",$D22*INDEX(Допущения!$C$25:$G$30,MATCH($C22,Допущения!$B$25:$B$30,0),5)) -> 2187.9113 | J22: =SUM(E22:I22) -> 9946.1363 | L22: Прочие SaaS
B23: SMS/USSD-агрегатор (подписка) | C23: инфляция | D23: 1800 | E23: =IF($D23="","",$D23*INDEX(Допущения!$C$25:$G$30,MATCH($C23,Допущения!$B$25:$B$30,0),1)) -> 1800 | F23: =IF($D23="","",$D23*INDEX(Допущения!$C$25:$G$30,MATCH($C23,Допущения!$B$25:$B$30,0),2)) -> 1890 | G23: =IF($D23="","",$D23*INDEX(Допущения!$C$25:$G$30,MATCH($C23,Допущения!$B$25:$B$30,0),3)) -> 1984.5 | H23: =IF($D23="","",$D23*INDEX(Допущения!$C$25:$G$30,MATCH($C23,Допущения!$B$25:$B$30,0),4)) -> 2083.725 | I23: =IF($D23="","",$D23*INDEX(Допущения!$C$25:$G$30,MATCH($C23,Допущения!$B$25:$B$30,0),5)) -> 2187.9113 | J23: =SUM(E23:I23) -> 9946.1363 | L23: SMS/USSD-агрегатор
B24: Итого по блоку | E24: =SUM(E18:E23) -> 12600 | F24: =SUM(F18:F23) -> 21930 | G24: =SUM(G18:G23) -> 37276.5 | H24: =SUM(H18:H23) -> 49640.325 | I24: =SUM(I18:I23) -> 62022.341 | J24: =SUM(J18:J23) -> 183469.17 | K24: =IFERROR(J24/$J$51,0) -> 0.0023873495
B26: БЛОК 3. Транзакционные расходы (Buy / Partner)
B27: Комиссии платёжных провайдеров | C27: GMV | D27: 594000 | E27: =IF($D27="","",$D27*INDEX(Допущения!$C$25:$G$30,MATCH($C27,Допущения!$B$25:$B$30,0),1)) -> 594000 | F27: =IF($D27="","",$D27*INDEX(Допущения!$C$25:$G$30,MATCH($C27,Допущения!$B$25:$B$30,0),2)) -> 2484000 | G27: =IF($D27="","",$D27*INDEX(Допущения!$C$25:$G$30,MATCH($C27,Допущения!$B$25:$B$30,0),3)) -> 6480000 | H27: =IF($D27="","",$D27*INDEX(Допущения!$C$25:$G$30,MATCH($C27,Допущения!$B$25:$B$30,0),4)) -> 10800000 | I27: =IF($D27="","",$D27*INDEX(Допущения!$C$25:$G$30,MATCH($C27,Допущения!$B$25:$B$30,0),5)) -> 14976000 | J27: =SUM(E27:I27) -> 35334000 | L27: 1,8% GMV (ADR-004): NG ≈60% GMV — Paystack 1,5% + ₦100 + НДС 7,5% ≈ 1,94% (основной), Flutterwave 2% + НДС ≈ 2,15% (резерв), наличные ≈1,5%; KE ≈40% — M-Pesa Buy Goods 0,55%; выплаты ≈0,1%; резерв на чарджбэки 0,2%. Лимит CFO ≤ 2,5% (A6 п.6)
B28: SMS-уведомления | C28: заказы | D28: 30000 | E28: =IF($D28="","",$D28*INDEX(Допущения!$C$25:$G$30,MATCH($C28,Допущения!$B$25:$B$30,0),1)) -> 30000 | F28: =IF($D28="","",$D28*INDEX(Допущения!$C$25:$G$30,MATCH($C28,Допущения!$B$25:$B$30,0),2)) -> 120000 | G28: =IF($D28="","",$D28*INDEX(Допущения!$C$25:$G$30,MATCH($C28,Допущения!$B$25:$B$30,0),3)) -> 300000 | H28: =IF($D28="","",$D28*INDEX(Допущения!$C$25:$G$30,MATCH($C28,Допущения!$B$25:$B$30,0),4)) -> 480000 | I28: =IF($D28="","",$D28*INDEX(Допущения!$C$25:$G$30,MATCH($C28,Допущения!$B$25:$B$30,0),5)) -> 640000 | J28: =SUM(E28:I28) -> 1570000 | L28: ≈3 SMS/заказ × $0,005 + OTP: $0,02/заказ (Africa's Talking, KE ≈ KES 0,8)
B29: WhatsApp-сообщения (за диалог) | C29: заказы | D29: 16500 | E29: =IF($D29="","",$D29*INDEX(Допущения!$C$25:$G$30,MATCH($C29,Допущения!$B$25:$B$30,0),1)) -> 16500 | F29: =IF($D29="","",$D29*INDEX(Допущения!$C$25:$G$30,MATCH($C29,Допущения!$B$25:$B$30,0),2)) -> 66000 | G29: =IF($D29="","",$D29*INDEX(Допущения!$C$25:$G$30,MATCH($C29,Допущения!$B$25:$B$30,0),3)) -> 165000 | H29: =IF($D29="","",$D29*INDEX(Допущения!$C$25:$G$30,MATCH($C29,Допущения!$B$25:$B$30,0),4)) -> 264000 | I29: =IF($D29="","",$D29*INDEX(Допущения!$C$25:$G$30,MATCH($C29,Допущения!$B$25:$B$30,0),5)) -> 352000 | J29: =SUM(E29:I29) -> 863500 | L29: 2 utility-сообщения продавцу/заказ: Meta $0,004 (KE) – $0,0068 (NG)
B30: Логистика: интеграции и комиссии партнёров | C30: заказы | D30: 225000 | E30: =IF($D30="","",$D30*INDEX(Допущения!$C$25:$G$30,MATCH($C30,Допущения!$B$25:$B$30,0),1)) -> 225000 | F30: =IF($D30="","",$D30*INDEX(Допущения!$C$25:$G$30,MATCH($C30,Допущения!$B$25:$B$30,0),2)) -> 900000 | G30: =IF($D30="","",$D30*INDEX(Допущения!$C$25:$G$30,MATCH($C30,Допущения!$B$25:$B$30,0),3)) -> 2250000 | H30: =IF($D30="","",$D30*INDEX(Допущения!$C$25:$G$30,MATCH($C30,Допущения!$B$25:$B$30,0),4)) -> 3600000 | I30: =IF($D30="","",$D30*INDEX(Допущения!$C$25:$G$30,MATCH($C30,Допущения!$B$25:$B$30,0),5)) -> 4800000 | J30: =SUM(E30:I30) -> 11775000 | L30: Доставку оплачивает покупатель (pass-through). Платформа платит обратную доставку по «бесплатному возврату 30 дней» (A2 обещ. 4): 6% × $2,5
B31: USSD-сессии и короткие коды | C31: заказы | D31: 10500 | E31: =IF($D31="","",$D31*INDEX(Допущения!$C$25:$G$30,MATCH($C31,Допущения!$B$25:$B$30,0),1)) -> 10500 | F31: =IF($D31="","",$D31*INDEX(Допущения!$C$25:$G$30,MATCH($C31,Допущения!$B$25:$B$30,0),2)) -> 42000 | G31: =IF($D31="","",$D31*INDEX(Допущения!$C$25:$G$30,MATCH($C31,Допущения!$B$25:$B$30,0),3)) -> 105000 | H31: =IF($D31="","",$D31*INDEX(Допущения!$C$25:$G$30,MATCH($C31,Допущения!$B$25:$B$30,0),4)) -> 168000 | I31: =IF($D31="","",$D31*INDEX(Допущения!$C$25:$G$30,MATCH($C31,Допущения!$B$25:$B$30,0),5)) -> 224000 | J31: =SUM(E31:I31) -> 549500 | L31: USSD-сессии ($0,005) + аренда короткого кода KE
B32: Итого по блоку | E32: =SUM(E27:E31) -> 876000 | F32: =SUM(F27:F31) -> 3612000 | G32: =SUM(G27:G31) -> 9300000 | H32: =SUM(H27:H31) -> 15312000 | I32: =SUM(I27:I31) -> 20992000 | J32: =SUM(J27:J31) -> 50092000 | K32: =IFERROR(J32/$J$51,0) -> 0.6518104
B34: БЛОК 4. Команда (ФОТ)
B35: Разработка (FTE × годовая ставка) | C35: ФОТ | D35: =N35*Допущения!$C$42 -> 680000 | E35: =N35*Допущения!$C$42*Допущения!C$27 -> 680000 | F35: =O35*Допущения!$C$42*Допущения!D$27 -> 1122000 | G35: =P35*Допущения!$C$42*Допущения!E$27 -> 1748450 | H35: =Q35*Допущения!$C$42*Допущения!F$27 -> 2375835 | I35: =R35*Допущения!$C$42*Допущения!G$27 -> 3111212.5 | J35: =SUM(E35:I35) -> 9037497.5 | L35: FTE (колонки N–R) × ставка × индекс ФОТ | N35: 8 | O35: 12 | P35: 17 | Q35: 21 | R35: 25
B36: DevOps / SRE | C36: ФОТ | D36: =N36*Допущения!$C$43 -> 200000 | E36: =N36*Допущения!$C$43*Допущения!C$27 -> 200000 | F36: =O36*Допущения!$C$43*Допущения!D$27 -> 330000 | G36: =P36*Допущения!$C$43*Допущения!E$27 -> 484000 | H36: =Q36*Допущения!$C$43*Допущения!F$27 -> 798600 | I36: =R36*Допущения!$C$43*Допущения!G$27 -> 878460 | J36: =SUM(E36:I36) -> 2691060 | L36: FTE (колонки N–R) × ставка SRE × индекс ФОТ | N36: 2 | O36: 3 | P36: 4 | Q36: 6 | R36: 6
B37: Поддержка и дежурства 24/7 | C37: ФОТ | D37: 50000 | E37: 50000 | F37: 80000 | G37: 110000 | H37: 140000 | I37: 160000 | J37: =SUM(E37:I37) -> 540000 | L37: Дежурства
B38: Архитектура и менеджмент | C38: ФОТ | D38: 300000 | E38: =IF($D38="","",$D38*INDEX(Допущения!$C$25:$G$30,MATCH($C38,Допущения!$B$25:$B$30,0),1)) -> 300000 | F38: =IF($D38="","",$D38*INDEX(Допущения!$C$25:$G$30,MATCH($C38,Допущения!$B$25:$B$30,0),2)) -> 330000 | G38: =IF($D38="","",$D38*INDEX(Допущения!$C$25:$G$30,MATCH($C38,Допущения!$B$25:$B$30,0),3)) -> 363000 | H38: =IF($D38="","",$D38*INDEX(Допущения!$C$25:$G$30,MATCH($C38,Допущения!$B$25:$B$30,0),4)) -> 399300 | I38: =IF($D38="","",$D38*INDEX(Допущения!$C$25:$G$30,MATCH($C38,Допущения!$B$25:$B$30,0),5)) -> 439230 | J38: =SUM(E38:I38) -> 1831530 | L38: CTO + Solution Architect
C39: фикс | E39: =IF($D39="","",$D39*INDEX(Допущения!$C$25:$G$30,MATCH($C39,Допущения!$B$25:$B$30,0),1)) | F39: =IF($D39="","",$D39*INDEX(Допущения!$C$25:$G$30,MATCH($C39,Допущения!$B$25:$B$30,0),2)) | G39: =IF($D39="","",$D39*INDEX(Допущения!$C$25:$G$30,MATCH($C39,Допущения!$B$25:$B$30,0),3)) | H39: =IF($D39="","",$D39*INDEX(Допущения!$C$25:$G$30,MATCH($C39,Допущения!$B$25:$B$30,0),4)) | I39: =IF($D39="","",$D39*INDEX(Допущения!$C$25:$G$30,MATCH($C39,Допущения!$B$25:$B$30,0),5)) | J39: =SUM(E39:I39) -> 0 | L39: Своя статья
B40: Итого по блоку | E40: =SUM(E35:E39) -> 1230000 | F40: =SUM(F35:F39) -> 1862000 | G40: =SUM(G35:G39) -> 2705450 | H40: =SUM(H35:H39) -> 3713735 | I40: =SUM(I35:I39) -> 4588902.5 | J40: =SUM(J35:J39) -> 14100088 | K40: =IFERROR(J40/$J$51,0) -> 0.18347408
B42: БЛОК 5. Разовые затраты и комплаенс
B43: Юридический и комплаенс-аудит (NDPR, POPIA, KICA) | C43: фикс | D43: 30000 | E43: 30000 | F43: 15000 | G43: 15750 | H43: 16538 | I43: 17364 | J43: =SUM(E43:I43) -> 94652 | L43: Комплаенс (как в A)
B44: Пентест и аудит безопасности | C44: инфляция | D44: 20000 | E44: =IF($D44="","",$D44*INDEX(Допущения!$C$25:$G$30,MATCH($C44,Допущения!$B$25:$B$30,0),1)) -> 20000 | F44: =IF($D44="","",$D44*INDEX(Допущения!$C$25:$G$30,MATCH($C44,Допущения!$B$25:$B$30,0),2)) -> 21000 | G44: =IF($D44="","",$D44*INDEX(Допущения!$C$25:$G$30,MATCH($C44,Допущения!$B$25:$B$30,0),3)) -> 22050 | H44: =IF($D44="","",$D44*INDEX(Допущения!$C$25:$G$30,MATCH($C44,Допущения!$B$25:$B$30,0),4)) -> 23152.5 | I44: =IF($D44="","",$D44*INDEX(Допущения!$C$25:$G$30,MATCH($C44,Допущения!$B$25:$B$30,0),5)) -> 24310.125 | J44: =SUM(E44:I44) -> 110512.62 | L44: Пентест (больше поверхность)
B45: Миграция данных и интеграции при запуске | C45: фикс | D45: 20000 | E45: 20000 | F45: 0 | G45: 0 | H45: 0 | I45: 0 | J45: =SUM(E45:I45) -> 20000 | L45: Онбординг партнёров
B46: Обучение команды и найм | C46: фикс | D46: 25000 | E46: 25000 | F46: 20000 | G46: 20000 | H46: 20000 | I46: 20000 | J46: =SUM(E46:I46) -> 105000 | L46: Найм +4 сверх заморозки (A6 п.5) и обучение Kafka
C47: фикс | E47: =IF($D47="","",$D47*INDEX(Допущения!$C$25:$G$30,MATCH($C47,Допущения!$B$25:$B$30,0),1)) | F47: =IF($D47="","",$D47*INDEX(Допущения!$C$25:$G$30,MATCH($C47,Допущения!$B$25:$B$30,0),2)) | G47: =IF($D47="","",$D47*INDEX(Допущения!$C$25:$G$30,MATCH($C47,Допущения!$B$25:$B$30,0),3)) | H47: =IF($D47="","",$D47*INDEX(Допущения!$C$25:$G$30,MATCH($C47,Допущения!$B$25:$B$30,0),4)) | I47: =IF($D47="","",$D47*INDEX(Допущения!$C$25:$G$30,MATCH($C47,Допущения!$B$25:$B$30,0),5)) | J47: =SUM(E47:I47) -> 0 | L47: Своя статья
B48: Итого по блоку | E48: =SUM(E43:E47) -> 95000 | F48: =SUM(F43:F47) -> 56000 | G48: =SUM(G43:G47) -> 57800 | H48: =SUM(H43:H47) -> 59690.5 | I48: =SUM(I43:I47) -> 61674.125 | J48: =SUM(J43:J47) -> 330164.62 | K48: =IFERROR(J48/$J$51,0) -> 0.0042961898
B50: Резерв на непредвиденное (contingency) | E50: =(E15+E24+E32+E40+E48)*Допущения!$C$17 -> 345462 | F50: =(F15+F24+F32+F40+F48)*Допущения!$C$17 -> 863644.5 | G50: =(G15+G24+G32+G40+G48)*Допущения!$C$17 -> 1874989 | H50: =(H15+H24+H32+H40+H48)*Допущения!$C$17 -> 2964093.9 | I50: =(I15+I24+I32+I40+I48)*Допущения!$C$17 -> 3975797.8 | J50: =SUM(E50:I50) -> 10023987 | L50: Расчёт: сумма блоков 1–5 × ставка резерва с листа «Допущения»
B51: ИТОГО прямые затраты (TCO без учёта простоев) | E51: =E15+E24+E32+E40+E48+E50 -> 2648542 | F51: =F15+F24+F32+F40+F48+F50 -> 6621274.5 | G51: =G15+G24+G32+G40+G48+G50 -> 14374915 | H51: =H15+H24+H32+H40+H48+H50 -> 22724720 | I51: =I15+I24+I32+I40+I48+I50 -> 30481117 | J51: =SUM(E51:I51) -> 76850568
B52: БЛОК 6. Стоимость недоступности (риск)
B53: Ожидаемые потери от простоя (SLO и цена минуты — по годам, «Допущения» стр. 38–41) | E53: =(1-Допущения!C40)*525600*Допущения!C38*Допущения!$C$21 -> 49500 | F53: =(1-Допущения!D40)*525600*Допущения!D38*Допущения!$C$21 -> 207000 | G53: =(1-Допущения!E40)*525600*Допущения!E38*Допущения!$C$21 -> 540000 | H53: =(1-Допущения!F40)*525600*Допущения!F38*Допущения!$C$21 -> 180000 | I53: =(1-Допущения!G40)*525600*Допущения!G38*Допущения!$C$21 -> 249600 | J53: =SUM(E53:I53) -> 1226100 | L53: (1 − SLO года) × 525 600 мин × цена минуты года × переключатель
B54: ИТОГО TCO с учётом стоимости простоя | E54: =E51+E53 -> 2698042 | F54: =F51+F53 -> 6828274.5 | G54: =G51+G53 -> 14914915 | H54: =H51+H53 -> 22904720 | I54: =I51+I53 -> 30730717 | J54: =SUM(E54:I54) -> 78076668
B55: Коэффициент дисконтирования | E55: =1/(1+Допущения!$C$16)^0 -> 1 | F55: =1/(1+Допущения!$C$16)^1 -> 0.8 | G55: =1/(1+Допущения!$C$16)^2 -> 0.64 | H55: =1/(1+Допущения!$C$16)^3 -> 0.512 | I55: =1/(1+Допущения!$C$16)^4 -> 0.4096
B56: Дисконтированный TCO (NPV затрат) | E56: =E54*E55 -> 2698042 | F56: =F54*F55 -> 5462619.6 | G56: =G54*G55 -> 9545545.9 | H56: =H54*H55 -> 11727216 | I56: =I54*I55 -> 12587302 | J56: =SUM(E56:I56) -> 42020726
B58: Ключевые метрики
B59: TCO за 5 лет, прямые затраты | E59: =J51 -> 76850568 | L59: Основная цифра для сравнения вариантов в ADR
B60: TCO за 5 лет с учётом простоя | E60: =J54 -> 78076668 | L60: Показывает цену недоступности для mission critical
B61: NPV затрат за 5 лет | E61: =J56 -> 42020726 | L61: Затраты, приведённые к сегодняшнему дню
B62: Средние затраты в год | E62: =J51/5 -> 15370114 | L62: Ориентир для планирования бюджета
B63: Облако + SaaS, $/мес в Год 1 (A6 п.1: лимит включает SaaS) | E63: =(E15+E24)/12 -> 8506.6667 | L63: Сравнивается с лимитом CFO
B64: Проверка бюджета CFO на Год 1 | E64: =IF((E15+E24)/12<=Допущения!$C$18,"В бюджете CFO","ПРЕВЫШЕНИЕ бюджета") -> ПРЕВЫШЕНИЕ бюджета | L64: Если превышение — объясни в ADR, чем жертвуешь
B65: TCO на 1 заказ за 5 лет | E65: =IFERROR(J51/SUM(Допущения!$C$8:$G$8),0) -> 0.97898813 | L65: Юнит-экономика: сколько ИТ стоит в одном заказе
B66: TCO на 1 активного пользователя (Год 5) | E66: =IFERROR(I51/Допущения!$G$7,0) -> 3.3867908 | L66: Проверка масштабируемости модели
B67: Затраты ИТ как доля GMV за 5 лет | E67: =IFERROR(J51/SUM(Допущения!$C$10:$G$10),0) -> 0.039149551 | L67: Здоровый маркетплейс — единицы процентов
B68: Доля облачной инфраструктуры в TCO | E68: =IFERROR(J15/J51,0) -> 0.027597193 | L68: Обычно меньше, чем ожидают студенты
B69: Доля транзакционных расходов в TCO | E69: =IFERROR(J32/J51,0) -> 0.6518104 | L69: Растёт быстрее всего вместе с GMV
B70: Доля команды (ФОТ) в TCO | E70: =IFERROR(J40/J51,0) -> 0.18347408 | L70: Как правило, крупнейшая статья
B72: Вывод для ADR (заполнить текстом): какой вариант дешевле, за счёт чего, и какие допущения сильнее всего влияют на результат?
B73: Средний вариант: превышает лимит CFO ($8.5k/мес), +4 человека сверх заморозки (A6 п.5). Это целевое состояние для A через 6–12+ мес. по триггерам, а не стартовое.

Sheet TCO C — микросервисы CTO
B2: TCO на 5 лет — C. Предложение CTO: 40–50 микросервисов, Istio, 3 кластера, self-hosted, Oracle, build-not-buy
B3: Заполняем колонки «Драйвер роста» и «База, $/год (Год 1)». Годы 1–5 считаются автоматически.
N4: Численность, FTE (среднее за год)
B5: Статья затрат | C5: Драйвер роста | D5: База, $/год (Год 1) | E5: Год 1 | F5: Год 2 | G5: Год 3 | H5: Год 4 | I5: Год 5 | J5: Итого 5 лет | K5: Доля | L5: Комментарий / источник | N5: Год 1 | O5: Год 2 | P5: Год 3 | Q5: Год 4 | R5: Год 5
B6: БЛОК 1. Облачная инфраструктура (OpEx)
B7: Compute: ноды / контейнеры / serverless | C7: пользователи | D7: 153600 | E7: =IF($D7="","",$D7*INDEX(Допущения!$C$25:$G$30,MATCH($C7,Допущения!$B$25:$B$30,0),1)) -> 153600 | F7: =IF($D7="","",$D7*INDEX(Допущения!$C$25:$G$30,MATCH($C7,Допущения!$B$25:$B$30,0),2)) -> 384000 | G7: =IF($D7="","",$D7*INDEX(Допущения!$C$25:$G$30,MATCH($C7,Допущения!$B$25:$B$30,0),3)) -> 768000 | H7: =IF($D7="","",$D7*INDEX(Допущения!$C$25:$G$30,MATCH($C7,Допущения!$B$25:$B$30,0),4)) -> 1075200 | I7: =IF($D7="","",$D7*INDEX(Допущения!$C$25:$G$30,MATCH($C7,Допущения!$B$25:$B$30,0),5)) -> 1382400 | J7: =SUM(E7:I7) -> 3763200 | L7: Под 10 млн с первого дня (A5): 2 кластера × ~40 × m7g.xlarge (AWS af-south-1 + GCP africa-south1), Istio-сайдкары +30%
B8: Управляемые БД (PostgreSQL, реплики) | C8: пользователи | D8: 29280 | E8: =IF($D8="","",$D8*INDEX(Допущения!$C$25:$G$30,MATCH($C8,Допущения!$B$25:$B$30,0),1)) -> 29280 | F8: =IF($D8="","",$D8*INDEX(Допущения!$C$25:$G$30,MATCH($C8,Допущения!$B$25:$B$30,0),2)) -> 73200 | G8: =IF($D8="","",$D8*INDEX(Допущения!$C$25:$G$30,MATCH($C8,Допущения!$B$25:$B$30,0),3)) -> 146400 | H8: =IF($D8="","",$D8*INDEX(Допущения!$C$25:$G$30,MATCH($C8,Допущения!$B$25:$B$30,0),4)) -> 204960 | I8: =IF($D8="","",$D8*INDEX(Допущения!$C$25:$G$30,MATCH($C8,Допущения!$B$25:$B$30,0),5)) -> 263520 | J8: =SUM(E8:I8) -> 717360 | L8: Oracle EE на EC2 r6i.2xlarge ×4 (primary + Data Guard в 2 регионах) + self-hosted PostgreSQL, io2
B9: Хранилище объектов и резервные копии | C9: пользователи | D9: 3000 | E9: =IF($D9="","",$D9*INDEX(Допущения!$C$25:$G$30,MATCH($C9,Допущения!$B$25:$B$30,0),1)) -> 3000 | F9: =IF($D9="","",$D9*INDEX(Допущения!$C$25:$G$30,MATCH($C9,Допущения!$B$25:$B$30,0),2)) -> 7500 | G9: =IF($D9="","",$D9*INDEX(Допущения!$C$25:$G$30,MATCH($C9,Допущения!$B$25:$B$30,0),3)) -> 15000 | H9: =IF($D9="","",$D9*INDEX(Допущения!$C$25:$G$30,MATCH($C9,Допущения!$B$25:$B$30,0),4)) -> 21000 | I9: =IF($D9="","",$D9*INDEX(Допущения!$C$25:$G$30,MATCH($C9,Допущения!$B$25:$B$30,0),5)) -> 27000 | J9: =SUM(E9:I9) -> 73500 | L9: Объектное хранилище в 2 облаках
B10: CDN и исходящий трафик | C10: пользователи | D10: 9800 | E10: =IF($D10="","",$D10*INDEX(Допущения!$C$25:$G$30,MATCH($C10,Допущения!$B$25:$B$30,0),1)) -> 9800 | F10: =IF($D10="","",$D10*INDEX(Допущения!$C$25:$G$30,MATCH($C10,Допущения!$B$25:$B$30,0),2)) -> 24500 | G10: =IF($D10="","",$D10*INDEX(Допущения!$C$25:$G$30,MATCH($C10,Допущения!$B$25:$B$30,0),3)) -> 49000 | H10: =IF($D10="","",$D10*INDEX(Допущения!$C$25:$G$30,MATCH($C10,Допущения!$B$25:$B$30,0),4)) -> 68600 | I10: =IF($D10="","",$D10*INDEX(Допущения!$C$25:$G$30,MATCH($C10,Допущения!$B$25:$B$30,0),5)) -> 88200 | J10: =SUM(E10:I10) -> 240100 | L10: CDN (как в A)
B11: Очереди / стриминг (Kafka, SQS) | C11: пользователи | D11: 13800 | E11: =IF($D11="","",$D11*INDEX(Допущения!$C$25:$G$30,MATCH($C11,Допущения!$B$25:$B$30,0),1)) -> 13800 | F11: =IF($D11="","",$D11*INDEX(Допущения!$C$25:$G$30,MATCH($C11,Допущения!$B$25:$B$30,0),2)) -> 34500 | G11: =IF($D11="","",$D11*INDEX(Допущения!$C$25:$G$30,MATCH($C11,Допущения!$B$25:$B$30,0),3)) -> 69000 | H11: =IF($D11="","",$D11*INDEX(Допущения!$C$25:$G$30,MATCH($C11,Допущения!$B$25:$B$30,0),4)) -> 96600 | I11: =IF($D11="","",$D11*INDEX(Допущения!$C$25:$G$30,MATCH($C11,Допущения!$B$25:$B$30,0),5)) -> 124200 | J11: =SUM(E11:I11) -> 338100 | L11: Self-hosted Kafka ×2 кластера + MirrorMaker 2
B12: Резервный регион / DR | C12: пользователи | D12: 6120 | E12: =IF($D12="","",$D12*INDEX(Допущения!$C$25:$G$30,MATCH($C12,Допущения!$B$25:$B$30,0),1)) -> 6120 | F12: =IF($D12="","",$D12*INDEX(Допущения!$C$25:$G$30,MATCH($C12,Допущения!$B$25:$B$30,0),2)) -> 15300 | G12: =IF($D12="","",$D12*INDEX(Допущения!$C$25:$G$30,MATCH($C12,Допущения!$B$25:$B$30,0),3)) -> 30600 | H12: =IF($D12="","",$D12*INDEX(Допущения!$C$25:$G$30,MATCH($C12,Допущения!$B$25:$B$30,0),4)) -> 42840 | I12: =IF($D12="","",$D12*INDEX(Допущения!$C$25:$G$30,MATCH($C12,Допущения!$B$25:$B$30,0),5)) -> 55080 | J12: =SUM(E12:I12) -> 149940 | L12: Active-active: межоблачный egress репликации ≈3 ТБ/мес + глобальный DNS-failover
B13: Локальное размещение данных (NDPR, Нигерия) | C13: инфляция | D13: 24000 | E13: =IF($D13="","",$D13*INDEX(Допущения!$C$25:$G$30,MATCH($C13,Допущения!$B$25:$B$30,0),1)) -> 24000 | F13: =IF($D13="","",$D13*INDEX(Допущения!$C$25:$G$30,MATCH($C13,Допущения!$B$25:$B$30,0),2)) -> 25200 | G13: =IF($D13="","",$D13*INDEX(Допущения!$C$25:$G$30,MATCH($C13,Допущения!$B$25:$B$30,0),3)) -> 26460 | H13: =IF($D13="","",$D13*INDEX(Допущения!$C$25:$G$30,MATCH($C13,Допущения!$B$25:$B$30,0),4)) -> 27783 | I13: =IF($D13="","",$D13*INDEX(Допущения!$C$25:$G$30,MATCH($C13,Допущения!$B$25:$B$30,0),5)) -> 29172.15 | J13: =SUM(E13:I13) -> 132615.15 | L13: On-prem кластер Лагос: колокация стойки + каналы (A5: «один on-prem под нигерийские данные»)
B14: Сеть, WAF, окружения (2 облака) | C14: пользователи | D14: 55200 | E14: =IF($D14="","",$D14*INDEX(Допущения!$C$25:$G$30,MATCH($C14,Допущения!$B$25:$B$30,0),1)) -> 55200 | F14: =IF($D14="","",$D14*INDEX(Допущения!$C$25:$G$30,MATCH($C14,Допущения!$B$25:$B$30,0),2)) -> 138000 | G14: =IF($D14="","",$D14*INDEX(Допущения!$C$25:$G$30,MATCH($C14,Допущения!$B$25:$B$30,0),3)) -> 276000 | H14: =IF($D14="","",$D14*INDEX(Допущения!$C$25:$G$30,MATCH($C14,Допущения!$B$25:$B$30,0),4)) -> 386400 | I14: =IF($D14="","",$D14*INDEX(Допущения!$C$25:$G$30,MATCH($C14,Допущения!$B$25:$B$30,0),5)) -> 496800 | J14: =SUM(E14:I14) -> 1352400 | L14: Сеть и WAF в двух облаках $7 200 + окружения: staging-кластеры, dev-лицензии, нагрузочный контур ≈ $4 000/мес
B15: Итого по блоку | E15: =SUM(E7:E14) -> 294800 | F15: =SUM(F7:F14) -> 702200 | G15: =SUM(G7:G14) -> 1380460 | H15: =SUM(H7:H14) -> 1923383 | I15: =SUM(I7:I14) -> 2466372.1 | J15: =SUM(J7:J14) -> 6767215.2 | K15: =IFERROR(J15/$J$51,0) -> 0.07573001
B17: БЛОК 2. Лицензии, SaaS и инструменты
B18: Observability (метрики, логи, трейсинг) | C18: пользователи | D18: 3600 | E18: =IF($D18="","",$D18*INDEX(Допущения!$C$25:$G$30,MATCH($C18,Допущения!$B$25:$B$30,0),1)) -> 3600 | F18: =IF($D18="","",$D18*INDEX(Допущения!$C$25:$G$30,MATCH($C18,Допущения!$B$25:$B$30,0),2)) -> 9000 | G18: =IF($D18="","",$D18*INDEX(Допущения!$C$25:$G$30,MATCH($C18,Допущения!$B$25:$B$30,0),3)) -> 18000 | H18: =IF($D18="","",$D18*INDEX(Допущения!$C$25:$G$30,MATCH($C18,Допущения!$B$25:$B$30,0),4)) -> 25200 | I18: =IF($D18="","",$D18*INDEX(Допущения!$C$25:$G$30,MATCH($C18,Допущения!$B$25:$B$30,0),5)) -> 32400 | J18: =SUM(E18:I18) -> 88200 | L18: OSS-стек self-hosted (Prometheus, Loki, Jaeger, Grafana) — железо в compute, здесь хранение и поддержка
B19: CI/CD, репозиторий, артефакты | C19: инфляция | D19: 3600 | E19: =IF($D19="","",$D19*INDEX(Допущения!$C$25:$G$30,MATCH($C19,Допущения!$B$25:$B$30,0),1)) -> 3600 | F19: =IF($D19="","",$D19*INDEX(Допущения!$C$25:$G$30,MATCH($C19,Допущения!$B$25:$B$30,0),2)) -> 3780 | G19: =IF($D19="","",$D19*INDEX(Допущения!$C$25:$G$30,MATCH($C19,Допущения!$B$25:$B$30,0),3)) -> 3969 | H19: =IF($D19="","",$D19*INDEX(Допущения!$C$25:$G$30,MATCH($C19,Допущения!$B$25:$B$30,0),4)) -> 4167.45 | I19: =IF($D19="","",$D19*INDEX(Допущения!$C$25:$G$30,MATCH($C19,Допущения!$B$25:$B$30,0),5)) -> 4375.8225 | J19: =SUM(E19:I19) -> 19892.273 | L19: GitHub + ArgoCD (self-hosted)
B20: Безопасность: WAF, секреты, антифрод | C20: пользователи | D20: 6000 | E20: =IF($D20="","",$D20*INDEX(Допущения!$C$25:$G$30,MATCH($C20,Допущения!$B$25:$B$30,0),1)) -> 6000 | F20: =IF($D20="","",$D20*INDEX(Допущения!$C$25:$G$30,MATCH($C20,Допущения!$B$25:$B$30,0),2)) -> 15000 | G20: =IF($D20="","",$D20*INDEX(Допущения!$C$25:$G$30,MATCH($C20,Допущения!$B$25:$B$30,0),3)) -> 30000 | H20: =IF($D20="","",$D20*INDEX(Допущения!$C$25:$G$30,MATCH($C20,Допущения!$B$25:$B$30,0),4)) -> 42000 | I20: =IF($D20="","",$D20*INDEX(Допущения!$C$25:$G$30,MATCH($C20,Допущения!$B$25:$B$30,0),5)) -> 54000 | J20: =SUM(E20:I20) -> 147000 | L20: Vault, WAF, сканеры, сертификаты mTLS
B21: WhatsApp Business API (подписка) | C21: инфляция | D21: 600 | E21: =IF($D21="","",$D21*INDEX(Допущения!$C$25:$G$30,MATCH($C21,Допущения!$B$25:$B$30,0),1)) -> 600 | F21: =IF($D21="","",$D21*INDEX(Допущения!$C$25:$G$30,MATCH($C21,Допущения!$B$25:$B$30,0),2)) -> 630 | G21: =IF($D21="","",$D21*INDEX(Допущения!$C$25:$G$30,MATCH($C21,Допущения!$B$25:$B$30,0),3)) -> 661.5 | H21: =IF($D21="","",$D21*INDEX(Допущения!$C$25:$G$30,MATCH($C21,Допущения!$B$25:$B$30,0),4)) -> 694.575 | I21: =IF($D21="","",$D21*INDEX(Допущения!$C$25:$G$30,MATCH($C21,Допущения!$B$25:$B$30,0),5)) -> 729.30375 | J21: =SUM(E21:I21) -> 3315.3787 | L21: BSP WhatsApp
B22: Прочее ПО и подписки | C22: инфляция | D22: 2400 | E22: =IF($D22="","",$D22*INDEX(Допущения!$C$25:$G$30,MATCH($C22,Допущения!$B$25:$B$30,0),1)) -> 2400 | F22: =IF($D22="","",$D22*INDEX(Допущения!$C$25:$G$30,MATCH($C22,Допущения!$B$25:$B$30,0),2)) -> 2520 | G22: =IF($D22="","",$D22*INDEX(Допущения!$C$25:$G$30,MATCH($C22,Допущения!$B$25:$B$30,0),3)) -> 2646 | H22: =IF($D22="","",$D22*INDEX(Допущения!$C$25:$G$30,MATCH($C22,Допущения!$B$25:$B$30,0),4)) -> 2778.3 | I22: =IF($D22="","",$D22*INDEX(Допущения!$C$25:$G$30,MATCH($C22,Допущения!$B$25:$B$30,0),5)) -> 2917.215 | J22: =SUM(E22:I22) -> 13261.515 | L22: Прочие SaaS
B23: Поддержка Oracle EE (22%/год) | C23: инфляция | D23: 83600 | E23: =IF($D23="","",$D23*INDEX(Допущения!$C$25:$G$30,MATCH($C23,Допущения!$B$25:$B$30,0),1)) -> 83600 | F23: =IF($D23="","",$D23*INDEX(Допущения!$C$25:$G$30,MATCH($C23,Допущения!$B$25:$B$30,0),2)) -> 87780 | G23: =IF($D23="","",$D23*INDEX(Допущения!$C$25:$G$30,MATCH($C23,Допущения!$B$25:$B$30,0),3)) -> 92169 | H23: =IF($D23="","",$D23*INDEX(Допущения!$C$25:$G$30,MATCH($C23,Допущения!$B$25:$B$30,0),4)) -> 96777.45 | I23: =IF($D23="","",$D23*INDEX(Допущения!$C$25:$G$30,MATCH($C23,Допущения!$B$25:$B$30,0),5)) -> 101616.32 | J23: =SUM(E23:I23) -> 461942.77 | L23: Поддержка Oracle EE 22%/год от $380 000 (A6 п.7: лицензии — «ожидайте отказ»)
B24: Итого по блоку | E24: =SUM(E18:E23) -> 99800 | F24: =SUM(F18:F23) -> 118710 | G24: =SUM(G18:G23) -> 147445.5 | H24: =SUM(H18:H23) -> 171617.78 | I24: =SUM(I18:I23) -> 196038.66 | J24: =SUM(J18:J23) -> 733611.94 | K24: =IFERROR(J24/$J$51,0) -> 0.0082096458
B26: БЛОК 3. Транзакционные расходы (Buy / Partner)
B27: Комиссии платёжных провайдеров | C27: GMV | D27: 594000 | E27: =IF($D27="","",$D27*INDEX(Допущения!$C$25:$G$30,MATCH($C27,Допущения!$B$25:$B$30,0),1)) -> 594000 | F27: =IF($D27="","",$D27*INDEX(Допущения!$C$25:$G$30,MATCH($C27,Допущения!$B$25:$B$30,0),2)) -> 2484000 | G27: =IF($D27="","",$D27*INDEX(Допущения!$C$25:$G$30,MATCH($C27,Допущения!$B$25:$B$30,0),3)) -> 6480000 | H27: =IF($D27="","",$D27*INDEX(Допущения!$C$25:$G$30,MATCH($C27,Допущения!$B$25:$B$30,0),4)) -> 10800000 | I27: =IF($D27="","",$D27*INDEX(Допущения!$C$25:$G$30,MATCH($C27,Допущения!$B$25:$B$30,0),5)) -> 14976000 | J27: =SUM(E27:I27) -> 35334000 | L27: 1,8% GMV (ADR-004): NG ≈60% GMV — Paystack 1,5% + ₦100 + НДС 7,5% ≈ 1,94% (основной), Flutterwave 2% + НДС ≈ 2,15% (резерв), наличные ≈1,5%; KE ≈40% — M-Pesa Buy Goods 0,55%; выплаты ≈0,1%; резерв на чарджбэки 0,2%. Лимит CFO ≤ 2,5% (A6 п.6)
B28: SMS-уведомления | C28: заказы | D28: 30000 | E28: =IF($D28="","",$D28*INDEX(Допущения!$C$25:$G$30,MATCH($C28,Допущения!$B$25:$B$30,0),1)) -> 30000 | F28: =IF($D28="","",$D28*INDEX(Допущения!$C$25:$G$30,MATCH($C28,Допущения!$B$25:$B$30,0),2)) -> 120000 | G28: =IF($D28="","",$D28*INDEX(Допущения!$C$25:$G$30,MATCH($C28,Допущения!$B$25:$B$30,0),3)) -> 300000 | H28: =IF($D28="","",$D28*INDEX(Допущения!$C$25:$G$30,MATCH($C28,Допущения!$B$25:$B$30,0),4)) -> 480000 | I28: =IF($D28="","",$D28*INDEX(Допущения!$C$25:$G$30,MATCH($C28,Допущения!$B$25:$B$30,0),5)) -> 640000 | J28: =SUM(E28:I28) -> 1570000 | L28: ≈3 SMS/заказ × $0,005 + OTP: $0,02/заказ (Africa's Talking, KE ≈ KES 0,8)
B29: WhatsApp-сообщения (за диалог) | C29: заказы | D29: 16500 | E29: =IF($D29="","",$D29*INDEX(Допущения!$C$25:$G$30,MATCH($C29,Допущения!$B$25:$B$30,0),1)) -> 16500 | F29: =IF($D29="","",$D29*INDEX(Допущения!$C$25:$G$30,MATCH($C29,Допущения!$B$25:$B$30,0),2)) -> 66000 | G29: =IF($D29="","",$D29*INDEX(Допущения!$C$25:$G$30,MATCH($C29,Допущения!$B$25:$B$30,0),3)) -> 165000 | H29: =IF($D29="","",$D29*INDEX(Допущения!$C$25:$G$30,MATCH($C29,Допущения!$B$25:$B$30,0),4)) -> 264000 | I29: =IF($D29="","",$D29*INDEX(Допущения!$C$25:$G$30,MATCH($C29,Допущения!$B$25:$B$30,0),5)) -> 352000 | J29: =SUM(E29:I29) -> 863500 | L29: 2 utility-сообщения продавцу/заказ: Meta $0,004 (KE) – $0,0068 (NG)
B30: Логистика: интеграции и комиссии партнёров | C30: заказы | D30: 225000 | E30: =IF($D30="","",$D30*INDEX(Допущения!$C$25:$G$30,MATCH($C30,Допущения!$B$25:$B$30,0),1)) -> 225000 | F30: =IF($D30="","",$D30*INDEX(Допущения!$C$25:$G$30,MATCH($C30,Допущения!$B$25:$B$30,0),2)) -> 900000 | G30: =IF($D30="","",$D30*INDEX(Допущения!$C$25:$G$30,MATCH($C30,Допущения!$B$25:$B$30,0),3)) -> 2250000 | H30: =IF($D30="","",$D30*INDEX(Допущения!$C$25:$G$30,MATCH($C30,Допущения!$B$25:$B$30,0),4)) -> 3600000 | I30: =IF($D30="","",$D30*INDEX(Допущения!$C$25:$G$30,MATCH($C30,Допущения!$B$25:$B$30,0),5)) -> 4800000 | J30: =SUM(E30:I30) -> 11775000 | L30: Доставку оплачивает покупатель (pass-through). Платформа платит обратную доставку по «бесплатному возврату 30 дней» (A2 обещ. 4): 6% × $2,5
B31: USSD-сессии и короткие коды | C31: заказы | D31: 10500 | E31: =IF($D31="","",$D31*INDEX(Допущения!$C$25:$G$30,MATCH($C31,Допущения!$B$25:$B$30,0),1)) -> 10500 | F31: =IF($D31="","",$D31*INDEX(Допущения!$C$25:$G$30,MATCH($C31,Допущения!$B$25:$B$30,0),2)) -> 42000 | G31: =IF($D31="","",$D31*INDEX(Допущения!$C$25:$G$30,MATCH($C31,Допущения!$B$25:$B$30,0),3)) -> 105000 | H31: =IF($D31="","",$D31*INDEX(Допущения!$C$25:$G$30,MATCH($C31,Допущения!$B$25:$B$30,0),4)) -> 168000 | I31: =IF($D31="","",$D31*INDEX(Допущения!$C$25:$G$30,MATCH($C31,Допущения!$B$25:$B$30,0),5)) -> 224000 | J31: =SUM(E31:I31) -> 549500 | L31: USSD-сессии ($0,005) + аренда короткого кода KE
B32: Итого по блоку | E32: =SUM(E27:E31) -> 876000 | F32: =SUM(F27:F31) -> 3612000 | G32: =SUM(G27:G31) -> 9300000 | H32: =SUM(H27:H31) -> 15312000 | I32: =SUM(I27:I31) -> 20992000 | J32: =SUM(J27:J31) -> 50092000 | K32: =IFERROR(J32/$J$51,0) -> 0.56056555
B34: БЛОК 4. Команда (ФОТ)
B35: Разработка (FTE × годовая ставка) | C35: ФОТ | D35: =N35*Допущения!$C$42 -> 1020000 | E35: =N35*Допущения!$C$42*Допущения!C$27 -> 1020000 | F35: =O35*Допущения!$C$42*Допущения!D$27 -> 1496000 | G35: =P35*Допущения!$C$42*Допущения!E$27 -> 2262700 | H35: =Q35*Допущения!$C$42*Допущения!F$27 -> 2941510 | I35: =R35*Допущения!$C$42*Допущения!G$27 -> 3733455 | J35: =SUM(E35:I35) -> 11453665 | L35: FTE (колонки N–R) × ставка × индекс ФОТ | N35: 12 | O35: 16 | P35: 22 | Q35: 26 | R35: 30
B36: DevOps / SRE | C36: ФОТ | D36: =N36*Допущения!$C$43 -> 500000 | E36: =N36*Допущения!$C$43*Допущения!C$27 -> 500000 | F36: =O36*Допущения!$C$43*Допущения!D$27 -> 660000 | G36: =P36*Допущения!$C$43*Допущения!E$27 -> 847000 | H36: =Q36*Допущения!$C$43*Допущения!F$27 -> 1064800 | I36: =R36*Допущения!$C$43*Допущения!G$27 -> 1171280 | J36: =SUM(E36:I36) -> 4243080 | L36: FTE (колонки N–R) × ставка SRE × индекс ФОТ | N36: 5 | O36: 6 | P36: 7 | Q36: 8 | R36: 8
B37: Поддержка и дежурства 24/7 | C37: ФОТ | D37: 120000 | E37: 120000 | F37: 150000 | G37: 180000 | H37: 200000 | I37: 220000 | J37: =SUM(E37:I37) -> 870000 | L37: Follow-the-sun для 3 кластеров с первого дня
B38: Архитектура и менеджмент | C38: ФОТ | D38: 420000 | E38: =IF($D38="","",$D38*INDEX(Допущения!$C$25:$G$30,MATCH($C38,Допущения!$B$25:$B$30,0),1)) -> 420000 | F38: =IF($D38="","",$D38*INDEX(Допущения!$C$25:$G$30,MATCH($C38,Допущения!$B$25:$B$30,0),2)) -> 462000 | G38: =IF($D38="","",$D38*INDEX(Допущения!$C$25:$G$30,MATCH($C38,Допущения!$B$25:$B$30,0),3)) -> 508200 | H38: =IF($D38="","",$D38*INDEX(Допущения!$C$25:$G$30,MATCH($C38,Допущения!$B$25:$B$30,0),4)) -> 559020 | I38: =IF($D38="","",$D38*INDEX(Допущения!$C$25:$G$30,MATCH($C38,Допущения!$B$25:$B$30,0),5)) -> 614922 | J38: =SUM(E38:I38) -> 2564142 | L38: CTO + Architect + Engineering Manager (координация 40–50 сервисов)
C39: фикс | E39: =IF($D39="","",$D39*INDEX(Допущения!$C$25:$G$30,MATCH($C39,Допущения!$B$25:$B$30,0),1)) | F39: =IF($D39="","",$D39*INDEX(Допущения!$C$25:$G$30,MATCH($C39,Допущения!$B$25:$B$30,0),2)) | G39: =IF($D39="","",$D39*INDEX(Допущения!$C$25:$G$30,MATCH($C39,Допущения!$B$25:$B$30,0),3)) | H39: =IF($D39="","",$D39*INDEX(Допущения!$C$25:$G$30,MATCH($C39,Допущения!$B$25:$B$30,0),4)) | I39: =IF($D39="","",$D39*INDEX(Допущения!$C$25:$G$30,MATCH($C39,Допущения!$B$25:$B$30,0),5)) | J39: =SUM(E39:I39) -> 0 | L39: Своя статья
B40: Итого по блоку | E40: =SUM(E35:E39) -> 2060000 | F40: =SUM(F35:F39) -> 2768000 | G40: =SUM(G35:G39) -> 3797900 | H40: =SUM(H35:H39) -> 4765330 | I40: =SUM(I35:I39) -> 5739657 | J40: =SUM(J35:J39) -> 19130887 | K40: =IFERROR(J40/$J$51,0) -> 0.2140884
B42: БЛОК 5. Разовые затраты и комплаенс
B43: Юридический и комплаенс-аудит (NDPR, POPIA, KICA) | C43: фикс | D43: 30000 | E43: 30000 | F43: 15000 | G43: 15750 | H43: 16538 | I43: 17364 | J43: =SUM(E43:I43) -> 94652 | L43: Комплаенс (как в A)
B44: Пентест и аудит безопасности | C44: инфляция | D44: 30000 | E44: =IF($D44="","",$D44*INDEX(Допущения!$C$25:$G$30,MATCH($C44,Допущения!$B$25:$B$30,0),1)) -> 30000 | F44: =IF($D44="","",$D44*INDEX(Допущения!$C$25:$G$30,MATCH($C44,Допущения!$B$25:$B$30,0),2)) -> 31500 | G44: =IF($D44="","",$D44*INDEX(Допущения!$C$25:$G$30,MATCH($C44,Допущения!$B$25:$B$30,0),3)) -> 33075 | H44: =IF($D44="","",$D44*INDEX(Допущения!$C$25:$G$30,MATCH($C44,Допущения!$B$25:$B$30,0),4)) -> 34728.75 | I44: =IF($D44="","",$D44*INDEX(Допущения!$C$25:$G$30,MATCH($C44,Допущения!$B$25:$B$30,0),5)) -> 36465.188 | J44: =SUM(E44:I44) -> 165768.94 | L44: Пентест: mesh, 3 кластера
B45: Миграция данных и интеграции при запуске | C45: фикс | D45: 40000 | E45: 40000 | F45: 0 | G45: 0 | H45: 0 | I45: 0 | J45: =SUM(E45:I45) -> 40000 | L45: Прямые интеграции M-Pesa/Flutterwave (оркестрация), своя логистика, сертификация
B46: Обучение команды и найм | C46: фикс | D46: 60000 | E46: 60000 | F46: 30000 | G46: 30000 | H46: 30000 | I46: 30000 | J46: =SUM(E46:I46) -> 180000 | L46: Найм 10+ человек (A5: «3–4 сильных Go в ближайшие 2 недели») + обучение Istio/Oracle
B47: Oracle EE лицензии + оборудование on-prem | C47: фикс | D47: 460000 | E47: 460000 | F47: 0 | G47: 0 | H47: 40000 | I47: 0 | J47: =SUM(E47:I47) -> 500000 | L47: Лицензии Oracle EE 8 processor × $47 500 + серверы on-prem Лагос $80 000; обновление железа в Г4
B48: Итого по блоку | E48: =SUM(E43:E47) -> 620000 | F48: =SUM(F43:F47) -> 76500 | G48: =SUM(G43:G47) -> 78825 | H48: =SUM(H43:H47) -> 121266.75 | I48: =SUM(I43:I47) -> 83829.188 | J48: =SUM(J43:J47) -> 980420.94 | K48: =IFERROR(J48/$J$51,0) -> 0.010971616
B50: Резерв на непредвиденное (contingency) | E50: =(E15+E24+E32+E40+E48)*Допущения!$C$17 -> 592590 | F50: =(F15+F24+F32+F40+F48)*Допущения!$C$17 -> 1091611.5 | G50: =(G15+G24+G32+G40+G48)*Допущения!$C$17 -> 2205694.6 | H50: =(H15+H24+H32+H40+H48)*Допущения!$C$17 -> 3344039.6 | I50: =(I15+I24+I32+I40+I48)*Допущения!$C$17 -> 4421684.6 | J50: =SUM(E50:I50) -> 11655620 | L50: Расчёт: сумма блоков 1–5 × ставка резерва с листа «Допущения»
B51: ИТОГО прямые затраты (TCO без учёта простоев) | E51: =E15+E24+E32+E40+E48+E50 -> 4543190 | F51: =F15+F24+F32+F40+F48+F50 -> 8369021.5 | G51: =G15+G24+G32+G40+G48+G50 -> 16910325 | H51: =H15+H24+H32+H40+H48+H50 -> 25637637 | I51: =I15+I24+I32+I40+I48+I50 -> 33899582 | J51: =SUM(E51:I51) -> 89359755
B52: БЛОК 6. Стоимость недоступности (риск)
B53: Ожидаемые потери от простоя (SLO и цена минуты — по годам, «Допущения» стр. 38–41) | E53: =(1-Допущения!C41)*525600*Допущения!C38*Допущения!$C$21 -> 9900 | F53: =(1-Допущения!D41)*525600*Допущения!D38*Допущения!$C$21 -> 41400 | G53: =(1-Допущения!E41)*525600*Допущения!E38*Допущения!$C$21 -> 108000 | H53: =(1-Допущения!F41)*525600*Допущения!F38*Допущения!$C$21 -> 180000 | I53: =(1-Допущения!G41)*525600*Допущения!G38*Допущения!$C$21 -> 249600 | J53: =SUM(E53:I53) -> 588900 | L53: (1 − SLO года) × 525 600 мин × цена минуты года × переключатель
B54: ИТОГО TCO с учётом стоимости простоя | E54: =E51+E53 -> 4553090 | F54: =F51+F53 -> 8410421.5 | G54: =G51+G53 -> 17018325 | H54: =H51+H53 -> 25817637 | I54: =I51+I53 -> 34149182 | J54: =SUM(E54:I54) -> 89948655
B55: Коэффициент дисконтирования | E55: =1/(1+Допущения!$C$16)^0 -> 1 | F55: =1/(1+Допущения!$C$16)^1 -> 0.8 | G55: =1/(1+Допущения!$C$16)^2 -> 0.64 | H55: =1/(1+Допущения!$C$16)^3 -> 0.512 | I55: =1/(1+Допущения!$C$16)^4 -> 0.4096
B56: Дисконтированный TCO (NPV затрат) | E56: =E54*E55 -> 4553090 | F56: =F54*F55 -> 6728337.2 | G56: =G54*G55 -> 10891728 | H56: =H54*H55 -> 13218630 | I56: =I54*I55 -> 13987505 | J56: =SUM(E56:I56) -> 49379290
B58: Ключевые метрики
B59: TCO за 5 лет, прямые затраты | E59: =J51 -> 89359755 | L59: Основная цифра для сравнения вариантов в ADR
B60: TCO за 5 лет с учётом простоя | E60: =J54 -> 89948655 | L60: Показывает цену недоступности для mission critical
B61: NPV затрат за 5 лет | E61: =J56 -> 49379290 | L61: Затраты, приведённые к сегодняшнему дню
B62: Средние затраты в год | E62: =J51/5 -> 17871951 | L62: Ориентир для планирования бюджета
B63: Облако + SaaS, $/мес в Год 1 (A6 п.1: лимит включает SaaS) | E63: =(E15+E24)/12 -> 32883.333 | L63: Сравнивается с лимитом CFO
B64: Проверка бюджета CFO на Год 1 | E64: =IF((E15+E24)/12<=Допущения!$C$18,"В бюджете CFO","ПРЕВЫШЕНИЕ бюджета") -> ПРЕВЫШЕНИЕ бюджета | L64: Если превышение — объясни в ADR, чем жертвуешь
B65: TCO на 1 заказ за 5 лет | E65: =IFERROR(J51/SUM(Допущения!$C$8:$G$8),0) -> 1.1383408 | L65: Юнит-экономика: сколько ИТ стоит в одном заказе
B66: TCO на 1 активного пользователя (Год 5) | E66: =IFERROR(I51/Допущения!$G$7,0) -> 3.7666202 | L66: Проверка масштабируемости модели
B67: Затраты ИТ как доля GMV за 5 лет | E67: =IFERROR(J51/SUM(Допущения!$C$10:$G$10),0) -> 0.045522035 | L67: Здоровый маркетплейс — единицы процентов
B68: Доля облачной инфраструктуры в TCO | E68: =IFERROR(J15/J51,0) -> 0.07573001 | L68: Обычно меньше, чем ожидают студенты
B69: Доля транзакционных расходов в TCO | E69: =IFERROR(J32/J51,0) -> 0.56056555 | L69: Растёт быстрее всего вместе с GMV
B70: Доля команды (ФОТ) в TCO | E70: =IFERROR(J40/J51,0) -> 0.2140884 | L70: Как правило, крупнейшая статья
B72: Вывод для ADR (заполнить текстом): какой вариант дешевле, за счёт чего, и какие допущения сильнее всего влияют на результат?
B73: Самый дорогой: облако+SaaS ≈ $32.9k/мес (6.6× лимита), Oracle $380k (A6 п.7: «ожидайте отказ»), +11 человек к заморозке. Окупается против A, только если средняя минута простоя дороже $18.0k весь период — дороже даже оценки инвестора $12k (лист «Сравнение»).

Sheet Сравнение
B2: Сравнение вариантов (формулы ссылаются на листы TCO)
B4: Метрика | C4: A — модульный монолит | D4: B — сервисы | E4: C — микросервисы CTO | F4: Комментарий
B5: TCO 5 лет, прямые затраты | C5: ='TCO A — модульный монолит'!J51 -> 73243019 | D5: ='TCO B — сервисы (SOA)'!J51 -> 76850568 | E5: ='TCO C — микросервисы CTO'!J51 -> 89359755 | F5: Блоки 1–5 + резерв
B6: в т.ч. ИТ без транзакционных (блоки 1, 2, 4, 5) | C6: ='TCO A — модульный монолит'!J15+'TCO A — модульный монолит'!J24+'TCO A — модульный монолит'!J40+'TCO A — модульный монолит'!J48 -> 13597582 | D6: ='TCO B — сервисы (SOA)'!J15+'TCO B — сервисы (SOA)'!J24+'TCO B — сервисы (SOA)'!J40+'TCO B — сервисы (SOA)'!J48 -> 16734581 | E6: ='TCO C — микросервисы CTO'!J15+'TCO C — микросервисы CTO'!J24+'TCO C — микросервисы CTO'!J40+'TCO C — микросервисы CTO'!J48 -> 27612135 | F6: Варианты различаются здесь; блок 3 одинаков (pass-through)
B7: TCO 5 лет с простоем (цена минуты от GMV) | C7: ='TCO A — модульный монолит'!J54 -> 74518619 | D7: ='TCO B — сервисы (SOA)'!J54 -> 78076668 | E7: ='TCO C — микросервисы CTO'!J54 -> 89948655 | F7: Режим 2 на листе «Допущения»
B8: NPV затрат 5 лет | C8: ='TCO A — модульный монолит'!J56 -> 39857575 | D8: ='TCO B — сервисы (SOA)'!J56 -> 42020726 | E8: ='TCO C — микросервисы CTO'!J56 -> 49379290 | F8: Ставка 25%
B9: Облако + SaaS, $/мес, Год 1 | C9: ='TCO A — модульный монолит'!E63 -> 4338.3333 | D9: ='TCO B — сервисы (SOA)'!E63 -> 8506.6667 | E9: ='TCO C — микросервисы CTO'!E63 -> 32883.333 | F9: Лимит CFO $5 000 (A6 п.1)
B10: Проверка лимита CFO | C10: ='TCO A — модульный монолит'!E64 -> В бюджете CFO | D10: ='TCO B — сервисы (SOA)'!E64 -> ПРЕВЫШЕНИЕ бюджета | E10: ='TCO C — микросервисы CTO'!E64 -> ПРЕВЫШЕНИЕ бюджета
B11: ФОТ, доля TCO | C11: ='TCO A — модульный монолит'!E70 -> 0.16271553 | D11: ='TCO B — сервисы (SOA)'!E70 -> 0.18347408 | E11: ='TCO C — микросервисы CTO'!E70 -> 0.2140884 | F11: Крупнейшая статья ИТ
B12: TCO на 1 заказ за 5 лет | C12: ='TCO A — модульный монолит'!E65 -> 0.93303209 | D12: ='TCO B — сервисы (SOA)'!E65 -> 0.97898813 | E12: ='TCO C — микросервисы CTO'!E65 -> 1.1383408 | F12: Включая транзакционные
B13: Затраты ИТ как доля GMV за 5 лет | C13: ='TCO A — модульный монолит'!E67 -> 0.037311777 | D13: ='TCO B — сервисы (SOA)'!E67 -> 0.039149551 | E13: ='TCO C — микросервисы CTO'!E67 -> 0.045522035
B15: Стоимость заказа (месячная модель: месяц 1 — 25 000 заказов, месяц 12 — 250 000)
B16: Метрика | C16: A | D16: B | E16: C | F16: Комментарий
B17: Месяц 1: инфраструктура + SaaS, $/мес | C17: 3688 | D17: 7231 | E17: 32883 | F17: A, B: 85% от среднего Г1 (E63); C: 100% — мощность под 10 млн с первого дня
B18: Месяц 1: команда (ФОТ, дежурства, менеджмент), $/мес | C18: 71250 | D18: 95416.67 | E18: 171666.67 | F18: A: 5 dev + 1 SRE (заморозка, A6 п.5); B: 7 + 2; C: 12 + 5; + дежурства и CTO/архитектор
B19: Месяц 1: ИТ-стоимость заказа, $ | C19: 3 | D19: 4.11 | E19: 8.18 | F19: (инфраструктура + команда) / 25 000 заказов
B20: Месяц 1: полная стоимость заказа с транзакционными, $ | C20: 3.58 | D20: 4.69 | E20: 8.77 | F20: + транзакционные на заказ (строка ниже)
B21: Месяц 12: инфраструктура + SaaS, $/мес | C21: 11385 | D21: 18969 | E21: 68409 | F21: Среднее Г2 из TCO: (блок 1 + блок 2, F15 + F24) / 12
B22: Месяц 12: команда, $/мес | C22: 120958.33 | D22: 155166.67 | E22: 230666.67 | F22: Среднее Г2 из TCO: блок 4 (F40) / 12; A = 11 FTE, как в roadmap
B23: Месяц 12: ИТ-стоимость заказа, $ | C23: 0.53 | D23: 0.7 | E23: 1.2 | F23: (инфраструктура + команда) / 250 000 заказов
B24: Месяц 12: полная стоимость заказа с транзакционными, $ | C24: 1.11 | D24: 1.28 | E24: 1.78 | F24: + транзакционные на заказ
B25: Транзакционные на заказ (PSP, SMS, WhatsApp, возвраты, USSD), $ | C25: 0.584 | D25: 0.584 | E25: 0.584 | F25: Одинаковы для всех вариантов (pass-through)
B27: Чувствительность к цене простоя
B28: TCO 5 лет, если каждая минута стоит $12k (оценка инвестора) | C28: 87118859 | D28: 87572808 | E28: 92513355 | F28: Даже при $12k каждую минуту C дороже A: вариант CTO окупается только от точки безубыточности ниже. Четвёртая девятка на A — отдельно, см. строку «4-я девятка»
B29: Точка безубыточности C против A: средняя цена минуты простоя, $ | E29: 18037 | F29: Δ прямых затрат C−A / Δ минут простоя A−C за 5 лет
B30: Точка безубыточности B против A, $/мин | D30: 13727
B31: 4-я девятка на A (99,95% → 99,99%): прирост затрат Г3 → Г4, $/год | C31: 404500 | F31: Второй регион active-active (строка 12), +2 SRE (строка 36), дежурства (строка 37)
B32: 4-я девятка на A: безубыточная средняя цена минуты, $ | C32: 1924 | F32: Прирост / 210 сэкономленных минут в год. По плану — Г3 ($2 055/мин); в TCO стоит Г4 — решение по фактической цене минуты. Если инвестор подтвердит $12k как среднюю минуту — окупается сразу, но это сверх лимита CFO (Q-02)
B34: Чувствительность: ИТ-затраты без транзакционных за 5 лет (теория «TCO»)
B35: База | C35: 13597582 | D35: 16734581 | E35: 27612135 | F35: Как в строке 6
B36: Нагрузка ×10 к плану | C36: 22754364 | D36: 31043653 | E36: 35112962 | F36: A, B: инфраструктура и SaaS × 10^0,85 + переделка (A $0,63 млн, B $0,3 млн); C: × 2 (уже под 10 млн)
B37: Срыв запуска на 3 мес. (C — на 6 мес.) | C37: 13845597 | D37: 17067601 | E37: 28839435 | F37: + месяцы команды и инфраструктуры Г1 без выручки
B38: Команда +30% (медленнее разработка) | C38: 17172915 | D38: 20964608 | E38: 33351401 | F38: Блок 4 × 1,3
B39: Вывод: во всех сценариях A дешевле B и C; разрыв сокращается только при нагрузке ×10 — это и есть триггер перехода A → B (ADR-001)

Sheet Стоимость ошибки
B2: Сколько стоит ошибиться (A6: «что мы потратили зря?» и «сколько стоит переделка?»)
B4: Сценарий 1. Строили под 10 млн, пришло 50 тыс. MAU — затраты Года 1
B5: Статья | C5: A под 50 тыс. | D5: B под 50 тыс. | E5: C под 50 тыс. | F5: Комментарий
B6: Инфраструктура | C6: 26400 | D6: 53688 | E6: 206360 | F6: C: 6 мес. полная мощность под 10 млн, затем срезка до 40%
B7: SaaS и лицензии (поддержка) | C7: 7200 | D7: 12600 | E7: 99800
B8: Команда | C8: 855000 | D8: 1098000 | E8: 1665000 | F8: C: 17 FTE полгода (уже наняты), затем 8
B9: Разовые (лицензии Oracle, железо, найм, онбординг) | C9: 70000 | D9: 95000 | E9: 620000 | F9: Oracle $380k и серверы $80k — невозвратные
B10: Итого Год 1 | C10: =SUM(C6:C9) -> 958600 | D10: =SUM(D6:D9) -> 1259288 | E10: =SUM(E6:E9) -> 2591160
B11: Потрачено зря относительно A | D11: =D10-C10 -> 300688 | E11: =E10-C10 -> 1632560
B13: Сценарий 2. Строили A (малое), а пришло 10 млн уже в Году 1 — цена ускоренной переделки
B14: Выделение 5 модулей в сервисы (5 × 3 чел-мес) | C14: 106250 | F14: Strangler: границы модулей и схем уже есть — переписывать не нужно
B15: Kafka + второй регион (6 чел-мес платформы) | C15: 50000
B16: Временный вертикальный рост БД/узлов (6 мес × $5k) | C16: 30000
B17: Доп. простой на переходе (99,9% вместо 99,99% при ×10 нагрузке, 50% вероятность) | C17: 445500 | F17: Цена минуты при 10 млн ×10 к плану Г1
B18: Итого цена переделки | C18: =SUM(C14:C17) -> 631750
B20: Вывод: ошибка «построили большое» ≈ $1,6 млн невозвратно за Год 1 (лицензии, найм, железо). Ошибка «построили малое» ≈ $0,19 млн работ + до $0,45 млн риска простоя на переходе — в 2,5 раза дешевле и обратима за 3–6 мес. по триггерам из ADR-001.
